{
	"pageNumber": 487,
	"data": "<div style='font-size:4.8vw; display: flex; justify-content: space-between; flex-direction: row-reverse;'><div>وَمِنۡ</div><div style='flex-grow:0.7'> ءَايَٰتِهِ <a data-content='السّـفن الجَاريَة' tabindex='0' role='button' class='fake-link tafsir' data-toggle='popover' data-placement='top'>ٱلۡجَوَارِ</a> فِي ٱلۡبَحۡرِ <a data-content='كالجبال أو القصور العالية' tabindex='0' role='button' class='fake-link tafsir' data-toggle='popover' data-placement='top'>كَٱلۡأَعۡلَٰمِ</a> ٣٢ إِن يَشَأۡ يُسۡكِنِ </div><div>ٱلرِّيحَ</div></div><div style='font-size:4.8vw; display: flex; justify-content: space-between; flex-direction: row-reverse;'><div><a data-content='فيَـصِرْن ثوَابت سَوَاكن' tabindex='0' role='button' class='fake-link tafsir' data-toggle='popover' data-placement='top'>فَيَظۡلَلۡنَ رَوَاكِدَ</a> عَلَىٰ ظَهۡرِهِۦٓۚ إِنَّ فِي ذَٰلِكَ لَأٓيَٰتٖ لِّكُلِّ صَبَّارٖ شَكُورٍ</div><div style='flex-grow:0.7'></div><div>شَكُورٍ</div></div><div style='font-size:4.8vw; display: flex; justify-content: space-between; flex-direction: row-reverse;'><div>٣٣</div><div style='flex-grow:0.7'> أَوۡ <a data-content='يُهلكْهنّ بالغرَق أي أهلهنّ' tabindex='0' role='button' class='fake-link tafsir' data-toggle='popover' data-placement='top'>يُوبِقۡهُنَّ</a> بِمَا كَسَبُواْ وَيَعۡفُ عَن كَثِيرٖ ٣٤ وَيَعۡلَمَ </div><div>ٱلَّذِينَ</div></div><div style='font-size:4.6vw; display: flex; justify-content: space-between; flex-direction: row-reverse;'><div>يُجَٰدِلُونَ</div><div style='flex-grow:0.7'> فِيٓ ءَايَٰتِنَا مَا لَهُم مِّن <a data-content='مَهْرَب ومَخلَصٍ من العذاب' tabindex='0' role='button' class='fake-link tafsir' data-toggle='popover' data-placement='top'>مَّحِيصٖ</a> ٣٥ فَمَآ أُوتِيتُم مِّن شَيۡءٖ </div><div>فَمَتَٰعُ</div></div><div style='font-size:4.8vw; display: flex; justify-content: space-between; flex-direction: row-reverse;'><div>ٱلۡحَيَوٰةِ</div><div style='flex-grow:0.7'> ٱلدُّنۡيَاۚ وَمَا عِندَ ٱللَّهِ خَيۡرٞ وَأَبۡقَىٰ لِلَّذِينَ ءَامَنُواْ وَعَلَىٰ </div><div>رَبِّهِمۡ</div></div><div style='font-size:4.8vw; display: flex; justify-content: space-between; flex-direction: row-reverse;'><div>يَتَوَكَّلُونَ</div><div style='flex-grow:0.7'> ٣٦ وَٱلَّذِينَ يَجۡتَنِبُونَ كَبَٰٓئِرَ ٱلۡإِثۡمِ <a data-content='مَا عَــُظمَ قبْحه من الذنوب' tabindex='0' role='button' class='fake-link tafsir' data-toggle='popover' data-placement='top'>وَٱلۡفَوَٰحِشَ</a> وَإِذَا </div><div>مَا</div></div><div style='font-size:4.8vw; display: flex; justify-content: space-between; flex-direction: row-reverse;'><div>غَضِبُواْ</div><div style='flex-grow:0.7'> هُمۡ يَغۡفِرُونَ ٣٧ وَٱلَّذِينَ ٱسۡتَجَابُواْ لِرَبِّهِمۡ وَأَقَامُواْ </div><div>ٱلصَّلَوٰةَ</div></div><div style='font-size:4.7vw; display: flex; justify-content: space-between; flex-direction: row-reverse;'><div><a data-content='يَتشاوَرون ويَترَاجعون فيه' tabindex='0' role='button' class='fake-link tafsir' data-toggle='popover' data-placement='top'>وَأَمۡرُهُمۡ شُورَىٰ</a> بَيۡنَهُمۡ وَمِمَّا رَزَقۡنَٰهُمۡ يُنفِقُونَ ٣٨ وَٱلَّذِينَ إِذَآ أَصَابَهُمُ</div><div style='flex-grow:0.7'></div><div>أَصَابَهُمُ</div></div><div style='font-size:4.8vw; display: flex; justify-content: space-between; flex-direction: row-reverse;'><div><a data-content='نـَـالهم الظلْم والعدْوَان' tabindex='0' role='button' class='fake-link tafsir' data-toggle='popover' data-placement='top'>ٱلۡبَغۡيُ</a> هُمۡ </div><div style='flex-grow:0.7'><a data-content='ينتقمون ممّن ظلمهمْ ولا يَعْـتدون' tabindex='0' role='button' class='fake-link tafsir' data-toggle='popover' data-placement='top'>يَنتَصِرُونَ</a> ٣٩ وَجَزَٰٓؤُاْ سَيِّئَةٖ سَيِّئَةٞ مِّثۡلُهَاۖ فَمَنۡ </div><div>عَفَا</div></div><div style='font-size:4.8vw; display: flex; justify-content: space-between; flex-direction: row-reverse;'><div>وَأَصۡلَحَ</div><div style='flex-grow:0.7'> فَأَجۡرُهُۥ عَلَى ٱللَّهِۚ إِنَّهُۥ لَا يُحِبُّ ٱلظَّٰلِمِينَ ٤٠ وَلَمَنِ </div><div>ٱنتَصَرَ</div></div><div style='font-size:4.8vw; display: flex; justify-content: space-between; flex-direction: row-reverse;'><div>بَعۡدَ</div><div style='flex-grow:0.7'> ظُلۡمِهِۦ فَأُوْلَٰٓئِكَ مَا عَلَيۡهِم مِّن سَبِيلٍ ٤١ إِنَّمَا ٱلسَّبِيلُ </div><div>عَلَى</div></div><div style='font-size:4.8vw; display: flex; justify-content: space-between; flex-direction: row-reverse;'><div>ٱلَّذِينَ</div><div style='flex-grow:0.7'> يَظۡلِمُونَ ٱلنَّاسَ <a data-content='يُـفـسدون أو يَتجبّـرون فيها' tabindex='0' role='button' class='fake-link tafsir' data-toggle='popover' data-placement='top'>وَيَبۡغُونَ فِي ٱلۡأَرۡضِ</a> بِغَيۡرِ ٱلۡحَقِّۚ </div><div>أُوْلَٰٓئِكَ</div></div><div style='font-size:4.8vw; display: flex; justify-content: space-between; flex-direction: row-reverse;'><div>لَهُمۡ</div><div style='flex-grow:0.7'> عَذَابٌ أَلِيمٞ ٤٢ وَلَمَن صَبَرَ وَغَفَرَ إِنَّ ذَٰلِكَ لَمِنۡ </div><div>عَزۡمِ</div></div><div style='font-size:4.8vw; display: flex; justify-content: space-between; flex-direction: row-reverse;'><div>ٱلۡأُمُورِ</div><div style='flex-grow:0.7'> ٤٣ وَمَن يُضۡلِلِ ٱللَّهُ فَمَا لَهُۥ مِن وَلِيّٖ مِّنۢ بَعۡدِهِۦۗ </div><div>وَتَرَى</div></div><div style='font-size:4.8vw; display: flex; justify-content: space-between; flex-direction: row-reverse;'><div>ٱلظَّٰلِمِينَ</div><div style='flex-grow:0.7'> لَمَّا رَأَوُاْ ٱلۡعَذَابَ يَقُولُونَ هَلۡ إِلَىٰ مَرَدّٖ مِّن سَبِيلٖ </div><div>٤٤</div></div><div style='font-size:4.8vw; display: flex; justify-content: space-between; flex-direction: row-reverse;'></div>",
	"hezb": "نصف الحزب 49",
	"goze": 25,
	"surahName": "الشُّورَىٰ"
}