{
	"pageNumber": 281,
	"data": "<div style='font-size:4.8vw; display: flex; justify-content: space-between; flex-direction: row-reverse;'><div>ثُمَّ</div><div style='flex-grow:0.7'> إِنَّ رَبَّكَ لِلَّذِينَ عَمِلُواْ ٱلسُّوٓءَ <a data-content='بتعدّي الطّور وركوب الرّأس' tabindex='0' role='button' class='fake-link tafsir' data-toggle='popover' data-placement='top'>بِجَهَٰلَةٖ</a> ثُمَّ تَابُواْ مِنۢ </div><div>بَعۡدِ</div></div><div style='font-size:4.8vw; display: flex; justify-content: space-between; flex-direction: row-reverse;'><div>ذَٰلِكَ</div><div style='flex-grow:0.7'> وَأَصۡلَحُوٓاْ إِنَّ رَبَّكَ مِنۢ بَعۡدِهَا لَغَفُورٞ رَّحِيمٌ ٩١١ </div><div>إِنَّ</div></div><div style='font-size:4.8vw; display: flex; justify-content: space-between; flex-direction: row-reverse;'><div>إِبۡرَٰهِيمَ</div><div style='flex-grow:0.7'> <a data-content='معلِّما للخير أو مؤمنا وحده' tabindex='0' role='button' class='fake-link tafsir' data-toggle='popover' data-placement='top'>كَانَ أُمَّةٗ</a> <a data-content='مُطيعا خاضعا له تعالى' tabindex='0' role='button' class='fake-link tafsir' data-toggle='popover' data-placement='top'>قَانِتٗا لِّلَّهِ</a> <a data-content='مائلا عن الباطل إلى الدّين الحقّ' tabindex='0' role='button' class='fake-link tafsir' data-toggle='popover' data-placement='top'>حَنِيفٗا</a> وَلَمۡ يَكُ مِنَ </div><div>ٱلۡمُشۡرِكِينَ</div></div><div style='font-size:4.8vw; display: flex; justify-content: space-between; flex-direction: row-reverse;'><div>٠٢١</div><div style='flex-grow:0.7'> شَاكِرٗا لِّأَنۡعُمِهِۚ <a data-content='اصطفاه واختاره للنُّبوّة' tabindex='0' role='button' class='fake-link tafsir' data-toggle='popover' data-placement='top'>ٱجۡتَبَىٰهُ</a> وَهَدَىٰهُ إِلَىٰ صِرَٰطٖ </div><div>مُّسۡتَقِيمٖ</div></div><div style='font-size:4.8vw; display: flex; justify-content: space-between; flex-direction: row-reverse;'><div>١٢١</div><div style='flex-grow:0.7'> وَءَاتَيۡنَٰهُ فِي ٱلدُّنۡيَا حَسَنَةٗۖ وَإِنَّهُۥ فِي ٱلۡأٓخِرَةِ لَمِنَ </div><div>ٱلصَّٰلِحِينَ</div></div><div style='font-size:4.8vw; display: flex; justify-content: space-between; flex-direction: row-reverse;'><div>٢٢١</div><div style='flex-grow:0.7'> ثُمَّ أَوۡحَيۡنَآ إِلَيۡكَ أَنِ ٱتَّبِعۡ <a data-content='شريعته وهي التّوحيد' tabindex='0' role='button' class='fake-link tafsir' data-toggle='popover' data-placement='top'>مِلَّةَ إِبۡرَٰهِيمَ</a> حَنِيفٗاۖ وَمَا </div><div>كَانَ</div></div><div style='font-size:4.8vw; display: flex; justify-content: space-between; flex-direction: row-reverse;'><div>مِنَ</div><div style='flex-grow:0.7'> ٱلۡمُشۡرِكِينَ ٣٢١ إِنَّمَا <a data-content='فُرض تعظيمُه والتّخلّي فيه للعبادة' tabindex='0' role='button' class='fake-link tafsir' data-toggle='popover' data-placement='top'>جُعِلَ ٱلسَّبۡتُ</a> عَلَى ٱلَّذِينَ </div><div>ٱخۡتَلَفُواْ</div></div><div style='font-size:4.8vw; display: flex; justify-content: space-between; flex-direction: row-reverse;'><div>فِيهِۚ</div><div style='flex-grow:0.7'> وَإِنَّ رَبَّكَ لَيَحۡكُمُ بَيۡنَهُمۡ يَوۡمَ ٱلۡقِيَٰمَةِ </div><div>فِيمَا</div></div><div style='font-size:4.8vw; display: flex; justify-content: space-between; flex-direction: row-reverse;'><div>كَانُواْ</div><div style='flex-grow:0.7'> فِيهِ يَخۡتَلِفُونَ ٤٢١ ٱدۡعُ إِلَىٰ سَبِيلِ رَبِّكَ </div><div>بِٱلۡحِكۡمَةِ</div></div><div style='font-size:4.8vw; display: flex; justify-content: space-between; flex-direction: row-reverse;'><div>وَٱلۡمَوۡعِظَةِ</div><div style='flex-grow:0.7'> ٱلۡحَسَنَةِۖ وَجَٰدِلۡهُم بِٱلَّتِي هِيَ أَحۡسَنُۚ </div><div>إِنَّ</div></div><div style='font-size:4.8vw; display: flex; justify-content: space-between; flex-direction: row-reverse;'><div>رَبَّكَ</div><div style='flex-grow:0.7'> هُوَ أَعۡلَمُ بِمَن ضَلَّ عَن سَبِيلِهِۦ وَهُوَ أَعۡلَمُ </div><div>بِٱلۡمُهۡتَدِينَ</div></div><div style='font-size:4.8vw; display: flex; justify-content: space-between; flex-direction: row-reverse;'><div>٥٢١</div><div style='flex-grow:0.7'> وَإِنۡ عَاقَبۡتُمۡ فَعَاقِبُواْ بِمِثۡلِ مَا عُوقِبۡتُم بِهِۦۖ </div><div>وَلَئِن</div></div><div style='font-size:4.8vw; display: flex; justify-content: space-between; flex-direction: row-reverse;'><div>صَبَرۡتُمۡ</div><div style='flex-grow:0.7'> لَهُوَ خَيۡرٞ لِّلصَّٰبِرِينَ ٦٢١ وَٱصۡبِرۡ وَمَا </div><div>صَبۡرُكَ</div></div><div style='font-size:4.8vw; display: flex; justify-content: space-between; flex-direction: row-reverse;'><div>إِلَّا</div><div style='flex-grow:0.7'> بِٱللَّهِۚ وَلَا تَحۡزَنۡ عَلَيۡهِمۡ وَلَا تَكُ فِي <a data-content='ضيق صدر وحَرَج' tabindex='0' role='button' class='fake-link tafsir' data-toggle='popover' data-placement='top'>ضَيۡقٖ</a> مِّمَّا </div><div>يَمۡكُرُونَ</div></div><div style='font-size:4.8vw; display: flex; justify-content: space-between; flex-direction: row-reverse;'><div>٧٢١</div><div style='flex-grow:0.7'> إِنَّ ٱللَّهَ مَعَ ٱلَّذِينَ ٱتَّقَواْ وَّٱلَّذِينَ هُم مُّحۡسِنُونَ </div><div>٨٢١</div></div><div style='font-size:4.8vw; display: flex; justify-content: space-between; flex-direction: row-reverse;'></div>",
	"hezb": "ثلاثة أرباع الحزب 28",
	"goze": 14,
	"surahName": "النَّحۡلِ"
}