{
	"pageNumber": 381,
	"data": "<div style='font-size:4.8vw; display: flex; justify-content: space-between; flex-direction: row-reverse;'><div>وَلَقَدۡ</div><div style='flex-grow:0.7'> أَرۡسَلۡنَآ إِلَىٰ ثَمُودَ أَخَاهُمۡ صَٰلِحًا أَنِ ٱعۡبُدُواْ </div><div>ٱللَّهَ</div></div><div style='font-size:4.8vw; display: flex; justify-content: space-between; flex-direction: row-reverse;'><div>فَإِذَا</div><div style='flex-grow:0.7'> هُمۡ فَرِيقَانِ يَخۡتَصِمُونَ ٤٥ قَالَ يَٰقَوۡمِ لِمَ </div><div>تَسۡتَعۡجِلُونَ</div></div><div style='font-size:4.8vw; display: flex; justify-content: space-between; flex-direction: row-reverse;'><div>بِٱلسَّيِّئَةِ</div><div style='flex-grow:0.7'> قَبۡلَ ٱلۡحَسَنَةِۖ لَوۡلَا تَسۡتَغۡفِرُونَ ٱللَّهَ </div><div>لَعَلَّكُمۡ</div></div><div style='font-size:4.8vw; display: flex; justify-content: space-between; flex-direction: row-reverse;'><div>تُرۡحَمُونَ</div><div style='flex-grow:0.7'> ٤٦ قَالُواْ <a data-content='تشاءمنا حيث أصبنا بالشّدائد' tabindex='0' role='button' class='fake-link tafsir' data-toggle='popover' data-placement='top'>ٱطَّيَّرۡنَا</a> بِكَ وَبِمَن مَّعَكَۚ قَالَ </div><div><a data-content='شؤمكم عملكم المكتوب عليكم عنده تعالى' tabindex='0' role='button' class='fake-link tafsir' data-toggle='popover' data-placement='top'>طَٰٓئِرُكُمۡ</a></div></div><div style='font-size:4.8vw; display: flex; justify-content: space-between; flex-direction: row-reverse;'><div>عِندَ</div><div style='flex-grow:0.7'> ٱللَّهِۖ بَلۡ أَنتُمۡ <a data-content='يفتنكم الشّيطان بوسوسته' tabindex='0' role='button' class='fake-link tafsir' data-toggle='popover' data-placement='top'>قَوۡمٞ تُفۡتَنُونَ</a> ٤٧ وَكَانَ فِي </div><div>ٱلۡمَدِينَةِ</div></div><div style='font-size:4.8vw; display: flex; justify-content: space-between; flex-direction: row-reverse;'><div><a data-content='أشخاص من الرّؤساء مع كلّ رهط' tabindex='0' role='button' class='fake-link tafsir' data-toggle='popover' data-placement='top'>تِسۡعَةُ رَهۡطٖ</a> يُفۡسِدُونَ فِي ٱلۡأَرۡضِ وَلَا يُصۡلِحُونَ ٤٨</div><div style='flex-grow:0.7'></div><div>٤٨</div></div><div style='font-size:4.8vw; display: flex; justify-content: space-between; flex-direction: row-reverse;'><div>قَالُواْ</div><div style='flex-grow:0.7'> <a data-content='تحالفوا بالله أو احلِفوا به' tabindex='0' role='button' class='fake-link tafsir' data-toggle='popover' data-placement='top'>تَقَاسَمُواْ بِٱللَّهِ</a> <a data-content='لنقتلنّهم ليلا بغتة' tabindex='0' role='button' class='fake-link tafsir' data-toggle='popover' data-placement='top'>لَنُبَيِّتَنَّهُۥ وَأَهۡلَهُۥ</a> ثُمَّ لَنَقُولَنَّ </div><div>لِوَلِيِّهِۦ</div></div><div style='font-size:4.8vw; display: flex; justify-content: space-between; flex-direction: row-reverse;'><div>مَا</div><div style='flex-grow:0.7'> شَهِدۡنَا <a data-content='هلاكهم' tabindex='0' role='button' class='fake-link tafsir' data-toggle='popover' data-placement='top'>مَهۡلِكَ أَهۡلِهِۦ</a> وَإِنَّا لَصَٰدِقُونَ ٤٩ </div><div>وَمَكَرُواْ</div></div><div style='font-size:4.8vw; display: flex; justify-content: space-between; flex-direction: row-reverse;'><div>مَكۡرٗا</div><div style='flex-grow:0.7'> وَمَكَرۡنَا مَكۡرٗا وَهُمۡ لَا يَشۡعُرُونَ ٥٠ </div><div>فَٱنظُرۡ</div></div><div style='font-size:4.8vw; display: flex; justify-content: space-between; flex-direction: row-reverse;'><div>كَيۡفَ</div><div style='flex-grow:0.7'> كَانَ عَٰقِبَةُ مَكۡرِهِمۡ أَنَّا <a data-content='أهلكناهم' tabindex='0' role='button' class='fake-link tafsir' data-toggle='popover' data-placement='top'>دَمَّرۡنَٰهُمۡ</a> </div><div>وَقَوۡمَهُمۡ</div></div><div style='font-size:4.8vw; display: flex; justify-content: space-between; flex-direction: row-reverse;'><div>أَجۡمَعِينَ</div><div style='flex-grow:0.7'> ٥١ فَتِلۡكَ بُيُوتُهُمۡ <a data-content='خالية خربَة أو ساقطة متهدّمة' tabindex='0' role='button' class='fake-link tafsir' data-toggle='popover' data-placement='top'>خَاوِيَةَۢ</a> بِمَا ظَلَمُوٓاْۚ </div><div>إِنَّ</div></div><div style='font-size:4.8vw; display: flex; justify-content: space-between; flex-direction: row-reverse;'><div>فِي</div><div style='flex-grow:0.7'> ذَٰلِكَ لَأٓيَةٗ لِّقَوۡمٖ يَعۡلَمُونَ ٥٢ وَأَنجَيۡنَا ٱلَّذِينَ </div><div>ءَامَنُواْ</div></div><div style='font-size:4.8vw; display: flex; justify-content: space-between; flex-direction: row-reverse;'><div>وَكَانُواْ</div><div style='flex-grow:0.7'> يَتَّقُونَ ٥٣ وَلُوطًا إِذۡ قَالَ لِقَوۡمِهِۦٓ </div><div>أَتَأۡتُونَ</div></div><div style='font-size:4.8vw; display: flex; justify-content: space-between; flex-direction: row-reverse;'><div>ٱلۡفَٰحِشَةَ</div><div style='flex-grow:0.7'> <a data-content='لا تبالون إظهارها مَجَانَة' tabindex='0' role='button' class='fake-link tafsir' data-toggle='popover' data-placement='top'>وَأَنتُمۡ تُبۡصِرُونَ</a> ٥٤ أَئِنَّكُمۡ لَتَأۡتُونَ </div><div>ٱلرِّجَالَ</div></div><div style='font-size:4.8vw; display: flex; justify-content: space-between; flex-direction: row-reverse;'><div>شَهۡوَةٗ</div><div style='flex-grow:0.7'> مِّن دُونِ ٱلنِّسَآءِۚ بَلۡ أَنتُمۡ قَوۡمٞ تَجۡهَلُونَ </div><div>٥٥</div></div><div style='font-size:4.8vw; display: flex; justify-content: space-between; flex-direction: row-reverse;'></div>",
	"hezb": "ثلاثة أرباع الحزب 38",
	"goze": 19,
	"surahName": "النَّمۡلِ"
}