{
	"pageNumber": 597,
	"data": "<div style='font-size:4.6vw'>
			<nobr>
				
				<a data-content='أثقـله حتـّـى سُـمِعَ له نقـيض (صَوْتٌ)' tabindex='0' role='button' class='fake-link tafsir' data-toggle='popover' data-placement='top'>
					ٱلَّذِيٓ أَنقَضَ ظَهۡرَكَ
				</a> 
				٣ وَرَفَعۡنَا لَكَ ذِكۡرَكَ ٤ فَإِنَّ مَعَ ٱلۡعُسۡرِ يُسۡرًا ٥ 
			</nobr>
		</div>
		<div style='font-size:4.6vw'>
			<nobr>
				إِنَّ مَعَ ٱلۡعُسۡرِ يُسۡرٗا ٦ 
				<a data-content='مِـنْ عِـبَـادة أدّيتها' tabindex='0' role='button' class='fake-link tafsir' data-toggle='popover' data-placement='top'>
					فَإِذَا فَرَغۡتَ
				</a> 
				
				<a data-content='فاجْتهِدْ وأتـْـبعْها بعِبادة أخرى' tabindex='0' role='button' class='fake-link tafsir' data-toggle='popover' data-placement='top'>
					فَٱنصَبۡ
				</a> 
				٧ وَإِلَىٰ رَبِّكَ 
				<a data-content='فاجْعَـلْ رَغْـبَـتـَك في جَميع شؤونك' tabindex='0' role='button' class='fake-link tafsir' data-toggle='popover' data-placement='top'>
					فَٱرۡغَب
				</a> 
				٨ 
			</nobr>
		</div>
		<div style='font-size:4.8vw' class='no-justify'>
			<nobr>
				سُورَةُ التِّينِ
			</nobr>
		</div>
		<div style='font-size:4.8vw' class='no-justify'>
			<nobr>
				بِسۡمِ ٱللَّهِ ٱلرَّحۡمَٰنِ ٱلرَّحِيمِ 
			</nobr>
		</div>
		<div style='font-size:4.8vw'>
			<nobr>
				
				<a data-content='(قسمٌ) بِمنْـبـَتـَيـْهما من الأرض المباركة' tabindex='0' role='button' class='fake-link tafsir' data-toggle='popover' data-placement='top'>
					وَٱلتِّينِ وَٱلزَّيۡتُونِ
				</a> 
				١ 
				<a data-content='جَبَلِ المُناجاة ِ للكَلِيم عليه السلام' tabindex='0' role='button' class='fake-link tafsir' data-toggle='popover' data-placement='top'>
					وَطُورِ سِينِينَ
				</a> 
				٢ وَهَٰذَا 
				<a data-content='مكة المكرّمة' tabindex='0' role='button' class='fake-link tafsir' data-toggle='popover' data-placement='top'>
					ٱلۡبَلَدِ ٱلۡأَمِينِ
				</a> 
				٣ 
			</nobr>
		</div>
		<div style='font-size:4.8vw'>
			<nobr>
				
				<a data-content='(جوابُ القسم) بالأربعةِ قَبلَه' tabindex='0' role='button' class='fake-link tafsir' data-toggle='popover' data-placement='top'>
					لَقَدۡ خَلَقۡنَا
				</a> 
				ٱلۡإِنسَٰنَ فِيٓ 
				<a data-content='أكْمَلِ تَعدِيلٍ وأحسنِ صُورَةٍ' tabindex='0' role='button' class='fake-link tafsir' data-toggle='popover' data-placement='top'>
					أَحۡسَنِ تَقۡوِيمٖ
				</a> 
				٤ ثُمَّ 
				<a data-content='ردَدْنا الكافرَ أو جـِنسَ الإنسان' tabindex='0' role='button' class='fake-link tafsir' data-toggle='popover' data-placement='top'>
					رَدَدۡنَٰهُ
				</a> 
				
				<a data-content='إلى النار أو الهَرمِ وأرذَلِ العُمُر' tabindex='0' role='button' class='fake-link tafsir' data-toggle='popover' data-placement='top'>
					أَسۡفَلَ سَٰفِلِينَ
				</a> 
				
			</nobr>
		</div>
		<div style='font-size:4.8vw'>
			<nobr>
				٥ إِلَّا ٱلَّذِينَ ءَامَنُواْ وَعَمِلُواْ ٱلصَّٰلِحَٰتِ فَلَهُمۡ أَجۡرٌ 
				<a data-content='غيرُ مَقطُوعٍ عنهم' tabindex='0' role='button' class='fake-link tafsir' data-toggle='popover' data-placement='top'>
					غَيۡرُ مَمۡنُونٖ
				</a> 
				٦ 
			</nobr>
		</div>
		<div style='font-size:4.8vw'>
			<nobr>
				فَمَا يُكَذِّبُكَ بَعۡدُ 
				<a data-content='بالجزاءِ بعد البعث والحساب' tabindex='0' role='button' class='fake-link tafsir' data-toggle='popover' data-placement='top'>
					بِٱلدِّينِ
				</a> 
				٧ أَلَيۡسَ ٱللَّهُ بِأَحۡكَمِ ٱلۡحَٰكِمِينَ ٨ 
			</nobr>
		</div>
		<div style='font-size:4.8vw' class='no-justify'>
			<nobr>
				سُورَةُ العَلَقِ
			</nobr>
		</div>
		<div style='font-size:4.8vw' class='no-justify'>
			<nobr>
				بِسۡمِ ٱللَّهِ ٱلرَّحۡمَٰنِ ٱلرَّحِيمِ 
			</nobr>
		</div>
		<div style='font-size:4.8vw'>
			<nobr>
				ٱقۡرَأۡ بِٱسۡمِ رَبِّكَ ٱلَّذِي خَلَقَ ١ خَلَقَ ٱلۡإِنسَٰنَ مِنۡ 
				<a data-content='دَمٍ جامِدٍ استحالَ إليه المَنِىُّ' tabindex='0' role='button' class='fake-link tafsir' data-toggle='popover' data-placement='top'>
					عَلَقٍ
				</a> 
				٢ ٱقۡرَأۡ 
			</nobr>
		</div>
		<div style='font-size:4.8vw'>
			<nobr>
				وَرَبُّكَ ٱلۡأَكۡرَمُ ٣ ٱلَّذِي 
				<a data-content='عَلَّـمَ الإنسانَ الكتابةَ بالقلم' tabindex='0' role='button' class='fake-link tafsir' data-toggle='popover' data-placement='top'>
					عَلَّمَ
				</a> 
				بِٱلۡقَلَمِ ٤ عَلَّمَ ٱلۡإِنسَٰنَ 
			</nobr>
		</div>
		<div style='font-size:4.8vw'>
			<nobr>
				مَا لَمۡ يَعۡلَمۡ ٥ 
				<a data-content='حقـّـًـا' tabindex='0' role='button' class='fake-link tafsir' data-toggle='popover' data-placement='top'>
					كَلَّآ
				</a> 
				إِنَّ ٱلۡإِنسَٰنَ 
				<a data-content='لَيُجَاوزُ الحدَّ فى العِصيان' tabindex='0' role='button' class='fake-link tafsir' data-toggle='popover' data-placement='top'>
					لَيَطۡغَىٰٓ
				</a> 
				٦ أَن رَّءَاهُ ٱسۡتَغۡنَىٰٓ 
			</nobr>
		</div>
		<div style='font-size:4.8vw'>
			<nobr>
				٧ إِنَّ إِلَىٰ رَبِّكَ 
				<a data-content='الرُّجُوعَ فى الآخرة للجزاء' tabindex='0' role='button' class='fake-link tafsir' data-toggle='popover' data-placement='top'>
					ٱلرُّجۡعَىٰٓ
				</a> 
				٨ 
				<a data-content='أخْبـِرْني' tabindex='0' role='button' class='fake-link tafsir' data-toggle='popover' data-placement='top'>
					أَرَءَيۡتَ
				</a> 
				ٱلَّذِي يَنۡهَىٰ ٩ عَبۡدًا 
			</nobr>
		</div>
		<div style='font-size:4.8vw'>
			<nobr>
				إِذَا صَلَّىٰٓ ٠١ أَرَءَيۡتَ إِن كَانَ عَلَى ٱلۡهُدَىٰٓ ١١ أَوۡ أَمَرَ بِٱلتَّقۡوَىٰٓ ٢١
			</nobr>
		</div>
		",
	"hezb": "نصف الحزب 60",
	"goze": 30,
	"surahName": "الشَّرۡحِ"
}