{
	"pageNumber": 71,
	"data": "<div style='font-size:4.8vw; display: flex; justify-content: space-between; flex-direction: row-reverse;'><div>وَلَئِن</div><div style='flex-grow:0.7'> مُّتُّمۡ أَوۡ قُتِلۡتُمۡ لَإِلَى ٱللَّهِ تُحۡشَرُونَ ١٥٨ <a data-content='فبرحمة عظيمة' tabindex='0' role='button' class='fake-link tafsir' data-toggle='popover' data-placement='top'>فَبِمَا رَحۡمَةٖ</a> مِّنَ </div><div>ٱللَّهِ</div></div><div style='font-size:4.8vw; display: flex; justify-content: space-between; flex-direction: row-reverse;'><div><a data-content='سهّلْتَ لهم أخلاقكَ ولم تُعنِّفهم' tabindex='0' role='button' class='fake-link tafsir' data-toggle='popover' data-placement='top'>لِنتَ لَهُمۡۖ</a> وَلَوۡ كُنتَ </div><div style='flex-grow:0.7'><a data-content='جافيا في المُعاشرة قولا وفعلا' tabindex='0' role='button' class='fake-link tafsir' data-toggle='popover' data-placement='top'>فَظًّا</a> غَلِيظَ ٱلۡقَلۡبِ <a data-content='لتفرّقوا ونفروا' tabindex='0' role='button' class='fake-link tafsir' data-toggle='popover' data-placement='top'>لَٱنفَضُّواْ</a> مِنۡ </div><div>حَوۡلِكَۖ</div></div><div style='font-size:4.8vw; display: flex; justify-content: space-between; flex-direction: row-reverse;'><div>فَٱعۡفُ</div><div style='flex-grow:0.7'> عَنۡهُمۡ وَٱسۡتَغۡفِرۡ لَهُمۡ وَشَاوِرۡهُمۡ فِي ٱلۡأَمۡرِۖ فَإِذَا </div><div>عَزَمۡتَ</div></div><div style='font-size:4.8vw; display: flex; justify-content: space-between; flex-direction: row-reverse;'><div>فَتَوَكَّلۡ</div><div style='flex-grow:0.7'> عَلَى ٱللَّهِۚ إِنَّ ٱللَّهَ يُحِبُّ ٱلۡمُتَوَكِّلِينَ ١٥٩ إِن يَنصُرۡكُمُ </div><div>ٱللَّهُ</div></div><div style='font-size:4.8vw; display: flex; justify-content: space-between; flex-direction: row-reverse;'><div><a data-content='فلا قاهر ولا خاذل لكم' tabindex='0' role='button' class='fake-link tafsir' data-toggle='popover' data-placement='top'>فَلَا غَالِبَ لَكُمۡۖ</a> وَإِن يَخۡذُلۡكُمۡ فَمَن ذَا ٱلَّذِي يَنصُرُكُم مِّنۢ</div><div style='flex-grow:0.7'></div><div>مِّنۢ</div></div><div style='font-size:4.8vw; display: flex; justify-content: space-between; flex-direction: row-reverse;'><div>بَعۡدِهِۦۗ</div><div style='flex-grow:0.7'> وَعَلَى ٱللَّهِ فَلۡيَتَوَكَّلِ ٱلۡمُؤۡمِنُونَ ١٦٠ وَمَا كَانَ لِنَبِيٍّ </div><div>أَن</div></div><div style='font-size:4.8vw; display: flex; justify-content: space-between; flex-direction: row-reverse;'><div><a data-content='يخون في الغنيمة' tabindex='0' role='button' class='fake-link tafsir' data-toggle='popover' data-placement='top'>يَغُلَّۚ</a> وَمَن يَغۡلُلۡ يَأۡتِ بِمَا غَلَّ يَوۡمَ ٱلۡقِيَٰمَةِۚ ثُمَّ تُوَفَّىٰ كُلُّ</div><div style='flex-grow:0.7'></div><div>كُلُّ</div></div><div style='font-size:4.8vw; display: flex; justify-content: space-between; flex-direction: row-reverse;'><div>نَفۡسٖ</div><div style='flex-grow:0.7'> مَّا كَسَبَتۡ وَهُمۡ لَا يُظۡلَمُونَ ١٦١ أَفَمَنِ ٱتَّبَعَ </div><div>رِضۡوَٰنَ</div></div><div style='font-size:4.8vw; display: flex; justify-content: space-between; flex-direction: row-reverse;'><div>ٱللَّهِ</div><div style='flex-grow:0.7'> كَمَنۢ <a data-content='رجع متلبِّسا بغضب شديد' tabindex='0' role='button' class='fake-link tafsir' data-toggle='popover' data-placement='top'>بَآءَ بِسَخَطٖ</a> مِّنَ ٱللَّهِ وَمَأۡوَىٰهُ جَهَنَّمُۖ وَبِئۡسَ </div><div>ٱلۡمَصِيرُ</div></div><div style='font-size:4.8vw; display: flex; justify-content: space-between; flex-direction: row-reverse;'><div>١٦٢</div><div style='flex-grow:0.7'> هُمۡ دَرَجَٰتٌ عِندَ ٱللَّهِۗ وَٱللَّهُ بَصِيرُۢ بِمَا يَعۡمَلُونَ ١٦٣ </div><div>لَقَدۡ</div></div><div style='font-size:4.8vw; display: flex; justify-content: space-between; flex-direction: row-reverse;'><div>مَنَّ</div><div style='flex-grow:0.7'> ٱللَّهُ عَلَى ٱلۡمُؤۡمِنِينَ إِذۡ بَعَثَ فِيهِمۡ رَسُولٗا مِّنۡ </div><div>أَنفُسِهِمۡ</div></div><div style='font-size:4.8vw; display: flex; justify-content: space-between; flex-direction: row-reverse;'><div>يَتۡلُواْ</div><div style='flex-grow:0.7'> عَلَيۡهِمۡ ءَايَٰتِهِۦ <a data-content='يُطهّرهم من أدناس الجاهلية' tabindex='0' role='button' class='fake-link tafsir' data-toggle='popover' data-placement='top'>وَيُزَكِّيهِمۡ</a> وَيُعَلِّمُهُمُ </div><div>ٱلۡكِتَٰبَ</div></div><div style='font-size:4.8vw; display: flex; justify-content: space-between; flex-direction: row-reverse;'><div>وَٱلۡحِكۡمَةَ</div><div style='flex-grow:0.7'> وَإِن كَانُواْ مِن قَبۡلُ لَفِي ضَلَٰلٖ مُّبِينٍ ١٦٤ </div><div>أَوَلَمَّآ</div></div><div style='font-size:4.8vw; display: flex; justify-content: space-between; flex-direction: row-reverse;'><div>أَصَٰبَتۡكُم</div><div style='flex-grow:0.7'> مُّصِيبَةٞ قَدۡ أَصَبۡتُم مِّثۡلَيۡهَا قُلۡتُمۡ </div><div><a data-content='من أين لنا هذا الخذلان' tabindex='0' role='button' class='fake-link tafsir' data-toggle='popover' data-placement='top'>أَنَّىٰ هَٰذَاۖ</a></div></div><div style='font-size:4.8vw; display: flex; justify-content: space-between; flex-direction: row-reverse;'><div>قُلۡ</div><div style='flex-grow:0.7'> هُوَ مِنۡ عِندِ أَنفُسِكُمۡۗ إِنَّ ٱللَّهَ عَلَىٰ كُلِّ شَيۡءٖ قَدِيرٞ </div><div>١٦٥</div></div><div style='font-size:4.8vw; display: flex; justify-content: space-between; flex-direction: row-reverse;'></div>",
	"hezb": "ثلاثة أرباع الحزب 7",
	"goze": 4,
	"surahName": "آلِ عِمۡرَانَ"
}