{
	"pageNumber": 304,
	"data": "<div style=\"font-size:4.5vw\">
			<nobr>
				قَالَ هَٰذَا رَحۡمَةٞ مِّن رَّبِّيۖ فَإِذَا جَآءَ وَعۡدُ رَبِّي 
				<a tabindex=\"0\" role=\"button\" class=\"fake-link tafsir\" data-toggle=\"popover\" data-placement=\"top\" data-content=\"مدكوكا مُسوّى بالأرض\">جَعَلَهُۥ دَكَّآءَۖ
				</a> وَكَانَ وَعۡدُ رَبِّي 
			</nobr>
		</div>
		<div style=\"font-size:4.8vw\">
			<nobr>
				حَقّٗا ٩٨ ۞وَتَرَكۡنَا بَعۡضَهُمۡ يَوۡمَئِذٖ 
				<a tabindex=\"0\" role=\"button\" class=\"fake-link tafsir\" data-toggle=\"popover\" data-placement=\"top\" data-content=\"يختلط ويضطرب\">يَمُوجُ
				</a> فِي بَعۡضٖۖ 
				<a tabindex=\"0\" role=\"button\" class=\"fake-link tafsir\" data-toggle=\"popover\" data-placement=\"top\" data-content=\"نفخة البعث\">وَنُفِخَ فِي ٱلصُّورِ
				</a> 
			</nobr>
		</div>
		<div style=\"font-size:4.8vw\">
			<nobr>
				فَجَمَعۡنَٰهُمۡ جَمۡعٗا ٩٩ وَعَرَضۡنَا جَهَنَّمَ يَوۡمَئِذٖ لِّلۡكَٰفِرِينَ عَرۡضًا ١٠٠ 
			</nobr>
		</div>
		<div style=\"font-size:4.6vw\">
			<nobr>
				ٱلَّذِينَ كَانَتۡ أَعۡيُنُهُمۡ فِي 
				<a tabindex=\"0\" role=\"button\" class=\"fake-link tafsir\" data-toggle=\"popover\" data-placement=\"top\" data-content=\"غشاء غليظ وستر كثيف\">غِطَآءٍ
				</a> عَن ذِكۡرِي وَكَانُواْ لَا يَسۡتَطِيعُونَ سَمۡعًا 
			</nobr>
		</div>
		<div style=\"font-size:4.7vw\">
			<nobr>
				١٠١ أَفَحَسِبَ ٱلَّذِينَ كَفَرُوٓاْ أَن يَتَّخِذُواْ عِبَادِي مِن دُونِيٓ أَوۡلِيَآءَۚ إِنَّآ 
			</nobr>
		</div>
		<div style=\"font-size:4.5vw\">
			<nobr>
				أَعۡتَدۡنَا جَهَنَّمَ لِلۡكَٰفِرِينَ 
				<a tabindex=\"0\" role=\"button\" class=\"fake-link tafsir\" data-toggle=\"popover\" data-placement=\"top\" data-content=\"منزلا أو شيئا يتمتّعون به\">نُزُلٗا
				</a> ١٠٢ قُلۡ هَلۡ نُنَبِّئُكُم بِٱلۡأَخۡسَرِينَ أَعۡمَٰلًا 
			</nobr>
		</div>
		<div style=\"font-size:4.7vw\">
			<nobr>
				١٠٣ ٱلَّذِينَ ضَلَّ سَعۡيُهُمۡ فِي ٱلۡحَيَوٰةِ ٱلدُّنۡيَا وَهُمۡ يَحۡسَبُونَ أَنَّهُمۡ يُحۡسِنُونَ 
			</nobr>
		</div>
		<div style=\"font-size:4.8vw\">
			<nobr>
				صُنۡعًا ١٠٤ أُوْلَٰٓئِكَ ٱلَّذِينَ كَفَرُواْ بِ‍َٔايَٰتِ رَبِّهِمۡ وَلِقَآئِهِۦ فَحَبِطَتۡ 
			</nobr>
		</div>
		<div style=\"font-size:4.8vw\">
			<nobr>
				أَعۡمَٰلُهُمۡ فَلَا نُقِيمُ لَهُمۡ يَوۡمَ ٱلۡقِيَٰمَةِ 
				<a tabindex=\"0\" role=\"button\" class=\"fake-link tafsir\" data-toggle=\"popover\" data-placement=\"top\" data-content=\"مقدارا واعتبارا لحبوط أعمالهم\">وَزۡنٗا
				</a> ١٠٥ ذَٰلِكَ جَزَآؤُهُمۡ جَهَنَّمُ 
			</nobr>
		</div>
		<div style=\"font-size:4.7vw\">
			<nobr>
				بِمَا كَفَرُواْ وَٱتَّخَذُوٓاْ ءَايَٰتِي وَرُسُلِي هُزُوًا ١٠٦ إِنَّ ٱلَّذِينَ ءَامَنُواْ وَعَمِلُواْ 
			</nobr>
		</div>
		<div style=\"font-size:4.8vw\">
			<nobr>
				ٱلصَّٰلِحَٰتِ كَانَتۡ لَهُمۡ جَنَّٰتُ 
				<a tabindex=\"0\" role=\"button\" class=\"fake-link tafsir\" data-toggle=\"popover\" data-placement=\"top\" data-content=\"أعلى الجنّة وأوسطها وأفضلها\">ٱلۡفِرۡدَوۡسِ
				</a> نُزُلًا ١٠٧ خَٰلِدِينَ فِيهَا 
			</nobr>
		</div>
		<div style=\"font-size:4.7vw\">
			<nobr>
				لَا يَبۡغُونَ عَنۡهَا 
				<a tabindex=\"0\" role=\"button\" class=\"fake-link tafsir\" data-toggle=\"popover\" data-placement=\"top\" data-content=\"تحوّلا وانتقالا\">حِوَلٗا
				</a> ١٠٨ قُل لَّوۡ كَانَ ٱلۡبَحۡرُ 
				<a tabindex=\"0\" role=\"button\" class=\"fake-link tafsir\" data-toggle=\"popover\" data-placement=\"top\" data-content=\"هو المّادة التي يكتب بها\">مِدَادٗا
				</a> 
				<a tabindex=\"0\" role=\"button\" class=\"fake-link tafsir\" data-toggle=\"popover\" data-placement=\"top\" data-content=\"معلوماته وحكمته تعالى\">لِّكَلِمَٰتِ رَبِّي
				</a> 
				<a tabindex=\"0\" role=\"button\" class=\"fake-link tafsir\" data-toggle=\"popover\" data-placement=\"top\" data-content=\"فنيَ وفَرغ\">لَنَفِدَ
				</a> 
			</nobr>
		</div>
		<div style=\"font-size:4.7vw\">
			<nobr>
				ٱلۡبَحۡرُ قَبۡلَ أَن تَنفَدَ كَلِمَٰتُ رَبِّي وَلَوۡ جِئۡنَا بِمِثۡلِهِۦ مَدَدٗا ١٠٩ قُلۡ إِنَّمَآ 
			</nobr>
		</div>
		<div style=\"font-size:4.7vw\">
			<nobr>
				أَنَا۠ بَشَرٞ مِّثۡلُكُمۡ يُوحَىٰٓ إِلَيَّ أَنَّمَآ إِلَٰهُكُمۡ إِلَٰهٞ وَٰحِدٞۖ فَمَن كَانَ يَرۡجُواْ 
			</nobr>
		</div>
		<div style=\"font-size:4.8vw\">
			<nobr>
				لِقَآءَ رَبِّهِۦ فَلۡيَعۡمَلۡ عَمَلٗا صَٰلِحٗا وَلَا يُشۡرِكۡ بِعِبَادَةِ رَبِّهِۦٓ أَحَدَۢا ١١٠
			</nobr>
		</div>
		",
	"hezb": "ربع الحزب 31",
	"goze": 16,
	"surahName": "الكَهۡفِ"
}