{
	"pageNumber": 534,
	"data": "<div style='font-size:4.8vw'><nobr>فِيهِنَّ <a data-content='خيّرات الأخلاق حِسان الوُجوه' tabindex='0' role='button' class='fake-link tafsir' data-toggle='popover' data-placement='top'>خَيۡرَٰتٌ حِسَانٞ</a> ٧٠ فَبِأَيِّ ءَالَآءِ رَبِّكُمَا تُكَذِّبَانِ </nobr></div><div style='font-size:4.8vw'><nobr>٧١ <a data-content='نساءٌ بيض حِسان' tabindex='0' role='button' class='fake-link tafsir' data-toggle='popover' data-placement='top'>حُورٞ</a> <a data-content='مخدّرات في بيوت من اللؤلؤ' tabindex='0' role='button' class='fake-link tafsir' data-toggle='popover' data-placement='top'>مَّقۡصُورَٰتٞ فِي ٱلۡخِيَامِ</a> ٧٢ فَبِأَيِّ ءَالَآءِ رَبِّكُمَا </nobr></div><div style='font-size:4.8vw'><nobr>تُكَذِّبَانِ ٧٣ لَمۡ يَطۡمِثۡهُنَّ إِنسٞ قَبۡلَهُمۡ وَلَا جَآنّٞ ٧٤ فَبِأَيِّ </nobr></div><div style='font-size:4.8vw'><nobr>ءَالَآءِ رَبِّكُمَا تُكَذِّبَانِ ٧٥ مُتَّكِ‍ِٔينَ عَلَىٰ <a data-content='وسائد أو فُرُش مُرتفعة' tabindex='0' role='button' class='fake-link tafsir' data-toggle='popover' data-placement='top'>رَفۡرَفٍ</a> خُضۡرٖ </nobr></div><div style='font-size:4.8vw'><nobr><a data-content='بُسطٍ ذات خمْل رقيق' tabindex='0' role='button' class='fake-link tafsir' data-toggle='popover' data-placement='top'>وَعَبۡقَرِيٍّ</a> حِسَانٖ ٧٦ فَبِأَيِّ ءَالَآءِ رَبِّكُمَا تُكَذِّبَانِ ٧٧ </nobr></div><div style='font-size:4.8vw'><nobr><a data-content='تعالى أو كثـُـرَ خيْرُه وإحسانه' tabindex='0' role='button' class='fake-link tafsir' data-toggle='popover' data-placement='top'>تَبَٰرَكَ</a> ٱسۡمُ رَبِّكَ <a data-content='العظمة والإستغناء المُطلق' tabindex='0' role='button' class='fake-link tafsir' data-toggle='popover' data-placement='top'>ذِي ٱلۡجَلَٰلِ</a> <a data-content='الفضل التام والإحسان' tabindex='0' role='button' class='fake-link tafsir' data-toggle='popover' data-placement='top'>وَٱلۡإِكۡرَامِ</a> ٧٨ </nobr></div><div style='font-size:4.8vw' class='no-justify'><nobr>سُورَةُ الوَاقِعَةِ</nobr></div><div style='font-size:4.8vw' class='no-justify'><nobr>بِسۡمِ ٱللَّهِ ٱلرَّحۡمَٰنِ ٱلرَّحِيمِ </nobr></div><div style='font-size:4.8vw'><nobr>إِذَا <a data-content='قامت القيامة بنفخة البعْث' tabindex='0' role='button' class='fake-link tafsir' data-toggle='popover' data-placement='top'>وَقَعَتِ ٱلۡوَاقِعَةُ</a> ١ لَيۡسَ لِوَقۡعَتِهَا <a data-content='نفْسٌ كاذبة تـُـنـْـكر وقوعها' tabindex='0' role='button' class='fake-link tafsir' data-toggle='popover' data-placement='top'>كَاذِبَةٌ</a> ٢ <a data-content='هي خافضة للأشقياء رافعة للسّعداء' tabindex='0' role='button' class='fake-link tafsir' data-toggle='popover' data-placement='top'>خَافِضَةٞ رَّافِعَةٌ</a> </nobr></div><div style='font-size:4.8vw'><nobr>٣ إِذَا <a data-content='زلزلتْ وحُرّكت تحريكا بشدة' tabindex='0' role='button' class='fake-link tafsir' data-toggle='popover' data-placement='top'>رُجَّتِ ٱلۡأَرۡضُ</a> رَجّٗا ٤ <a data-content='فـتـّـتْ كالسّويق المَـلْـتوت' tabindex='0' role='button' class='fake-link tafsir' data-toggle='popover' data-placement='top'>وَبُسَّتِ ٱلۡجِبَالُ</a> بَسّٗا ٥ فَكَانَتۡ </nobr></div><div style='font-size:4.8vw'><nobr><a data-content='غبارًا متفرقا منتشِرا' tabindex='0' role='button' class='fake-link tafsir' data-toggle='popover' data-placement='top'>هَبَآءٗ مُّنۢبَثّٗا</a> ٦ <a data-content='أصنافا' tabindex='0' role='button' class='fake-link tafsir' data-toggle='popover' data-placement='top'>وَكُنتُمۡ أَزۡوَٰجٗا</a> ثَلَٰثَةٗ ٧ <a data-content='اليُـمْن والبركة أو ناحية اليمين' tabindex='0' role='button' class='fake-link tafsir' data-toggle='popover' data-placement='top'>فَأَصۡحَٰبُ ٱلۡمَيۡمَنَةِ</a> </nobr></div><div style='font-size:4.8vw'><nobr>مَآ أَصۡحَٰبُ ٱلۡمَيۡمَنَةِ ٨ <a data-content='الشؤم أو ناحية الشمال' tabindex='0' role='button' class='fake-link tafsir' data-toggle='popover' data-placement='top'>وَأَصۡحَٰبُ ٱلۡمَشۡ‍َٔمَةِ</a> مَآ أَصۡحَٰبُ </nobr></div><div style='font-size:4.8vw'><nobr>ٱلۡمَشۡ‍َٔمَةِ ٩ وَٱلسَّٰبِقُونَ ٱلسَّٰبِقُونَ ١٠ أُوْلَٰٓئِكَ ٱلۡمُقَرَّبُونَ ١١ </nobr></div><div style='font-size:4.8vw'><nobr>فِي جَنَّٰتِ ٱلنَّعِيمِ ١٢ <a data-content='هم أمّة من الناس كثيرة' tabindex='0' role='button' class='fake-link tafsir' data-toggle='popover' data-placement='top'>ثُلَّةٞ</a> مِّنَ ٱلۡأَوَّلِينَ ١٣ وَقَلِيلٞ مِّنَ ٱلۡأٓخِرِينَ </nobr></div><div style='font-size:4.8vw'><nobr>١٤ عَلَىٰ <a data-content='منسوجة من الذهب بإحكام' tabindex='0' role='button' class='fake-link tafsir' data-toggle='popover' data-placement='top'>سُرُرٖ مَّوۡضُونَةٖ</a> ١٥ مُّتَّكِ‍ِٔينَ عَلَيۡهَا مُتَقَٰبِلِينَ ١٦</nobr></div>",
	"hezb": "ربع الحزب 54",
	"goze": 27,
	"surahName": "الرَّحۡمَٰن"
}