{
	"pageNumber": 308,
	"data": "<div style='font-size:4.8vw'>
			<nobr>
				وَأَنذِرۡهُمۡ 
				<a data-content='النّدامة الشّديدة على ما فات' tabindex='0' role='button' class='fake-link tafsir' data-toggle='popover' data-placement='top'>
					يَوۡمَ ٱلۡحَسۡرَةِ
				</a> 
				إِذۡ قُضِيَ ٱلۡأَمۡرُ وَهُمۡ فِي غَفۡلَةٖ وَهُمۡ لَا يُؤۡمِنُونَ 
			</nobr>
		</div>
		<div style='font-size:4.8vw'>
			<nobr>
				٩٣ إِنَّا نَحۡنُ نَرِثُ ٱلۡأَرۡضَ وَمَنۡ عَلَيۡهَا وَإِلَيۡنَا يُرۡجَعُونَ ٠٤ وَٱذۡكُرۡ 
			</nobr>
		</div>
		<div style='font-size:4.8vw'>
			<nobr>
				فِي ٱلۡكِتَٰبِ إِبۡرَٰهِيمَۚ إِنَّهُۥ كَانَ صِدِّيقٗا نَّبِيًّا ١٤ إِذۡ قَالَ لِأَبِيهِ يَٰٓأَبَتِ 
			</nobr>
		</div>
		<div style='font-size:4.8vw'>
			<nobr>
				لِمَ تَعۡبُدُ مَا لَا يَسۡمَعُ وَلَا يُبۡصِرُ وَلَا يُغۡنِي عَنكَ شَيۡ‍ٔٗا ٢٤ يَٰٓأَبَتِ 
			</nobr>
		</div>
		<div style='font-size:4.8vw'>
			<nobr>
				إِنِّي قَدۡ جَآءَنِي مِنَ ٱلۡعِلۡمِ مَا لَمۡ يَأۡتِكَ فَٱتَّبِعۡنِيٓ أَهۡدِكَ صِرَٰطٗا 
			</nobr>
		</div>
		<div style='font-size:4.8vw'>
			<nobr>
				
				<a data-content='طريقا مُستقيما مُنجيا من الضلال' tabindex='0' role='button' class='fake-link tafsir' data-toggle='popover' data-placement='top'>
					سَوِيّٗا
				</a> 
				٣٤ يَٰٓأَبَتِ لَا تَعۡبُدِ ٱلشَّيۡطَٰنَۖ إِنَّ ٱلشَّيۡطَٰنَ كَانَ لِلرَّحۡمَٰنِ 
			</nobr>
		</div>
		<div style='font-size:4.8vw'>
			<nobr>
				
				<a data-content='كثير العصيان' tabindex='0' role='button' class='fake-link tafsir' data-toggle='popover' data-placement='top'>
					عَصِيّٗا
				</a> 
				٤٤ يَٰٓأَبَتِ إِنِّيٓ أَخَافُ أَن يَمَسَّكَ عَذَابٞ مِّنَ ٱلرَّحۡمَٰنِ 
			</nobr>
		</div>
		<div style='font-size:4.8vw'>
			<nobr>
				فَتَكُونَ لِلشَّيۡطَٰنِ 
				<a data-content='قرينا تليه ويليك في النّار' tabindex='0' role='button' class='fake-link tafsir' data-toggle='popover' data-placement='top'>
					وَلِيّٗا
				</a> 
				٥٤ قَالَ أَرَاغِبٌ أَنتَ عَنۡ ءَالِهَتِي 
			</nobr>
		</div>
		<div style='font-size:4.8vw'>
			<nobr>
				يَٰٓإِبۡرَٰهِيمُۖ لَئِن لَّمۡ تَنتَهِ لَأَرۡجُمَنَّكَۖ 
				<a data-content='اجتنبني وفارقني دهرا طويلا' tabindex='0' role='button' class='fake-link tafsir' data-toggle='popover' data-placement='top'>
					وَٱهۡجُرۡنِي مَلِيّٗا
				</a> 
				٦٤ قَالَ 
			</nobr>
		</div>
		<div style='font-size:4.8vw'>
			<nobr>
				سَلَٰمٌ عَلَيۡكَۖ سَأَسۡتَغۡفِرُ لَكَ رَبِّيٓۖ إِنَّهُۥ كَانَ بِي 
				<a data-content='برّا لطيفا أو رحيما مُكرما' tabindex='0' role='button' class='fake-link tafsir' data-toggle='popover' data-placement='top'>
					حَفِيّٗا
				</a> 
				٧٤ 
			</nobr>
		</div>
		<div style='font-size:4.8vw'>
			<nobr>
				وَأَعۡتَزِلُكُمۡ وَمَا تَدۡعُونَ مِن دُونِ ٱللَّهِ وَأَدۡعُواْ رَبِّي عَسَىٰٓ أَلَّآ 
			</nobr>
		</div>
		<div style='font-size:4.8vw'>
			<nobr>
				أَكُونَ بِدُعَآءِ رَبِّي 
				<a data-content='خائبا ضائع السّعي' tabindex='0' role='button' class='fake-link tafsir' data-toggle='popover' data-placement='top'>
					شَقِيّٗا
				</a> 
				٨٤ فَلَمَّا ٱعۡتَزَلَهُمۡ وَمَا يَعۡبُدُونَ مِن 
			</nobr>
		</div>
		<div style='font-size:4.8vw'>
			<nobr>
				دُونِ ٱللَّهِ وَهَبۡنَا لَهُۥٓ إِسۡحَٰقَ وَيَعۡقُوبَۖ وَكُلّٗا جَعَلۡنَا نَبِيّٗا ٩٤ 
			</nobr>
		</div>
		<div style='font-size:4.8vw'>
			<nobr>
				وَوَهَبۡنَا لَهُم مِّن رَّحۡمَتِنَا وَجَعَلۡنَا لَهُمۡ 
				<a data-content='ثناءً حسنا في أهل كلّ دين' tabindex='0' role='button' class='fake-link tafsir' data-toggle='popover' data-placement='top'>
					لِسَانَ صِدۡقٍ
				</a> 
				عَلِيّٗا ٠٥ 
			</nobr>
		</div>
		<div style='font-size:4.8vw'>
			<nobr>
				وَٱذۡكُرۡ فِي ٱلۡكِتَٰبِ مُوسَىٰٓۚ إِنَّهُۥ 
				<a data-content='أخلصه الله واصطفاه' tabindex='0' role='button' class='fake-link tafsir' data-toggle='popover' data-placement='top'>
					كَانَ مُخۡلَصٗا
				</a> 
				وَكَانَ رَسُولٗا نَّبِيّٗا ١٥
			</nobr>
		</div>
		",
	"hezb": "نصف الحزب 31",
	"goze": 16,
	"surahName": "مَرۡيَمَ"
}