{
	"pageNumber": 361,
	"data": "<div style='font-size:4.8vw; display: flex; justify-content: space-between; flex-direction: row-reverse;'><div>إِذَا</div><div style='flex-grow:0.7'> رَأَتۡهُم مِّن مَّكَانِۢ بَعِيدٖ سَمِعُواْ لَهَا <a data-content='صوت غليان كصوت المتغيّظ' tabindex='0' role='button' class='fake-link tafsir' data-toggle='popover' data-placement='top'>تَغَيُّظٗا</a> <a data-content='صوتا شديدا كصوت الزّافر' tabindex='0' role='button' class='fake-link tafsir' data-toggle='popover' data-placement='top'>وَزَفِيرٗا</a> </div><div>٢١</div></div><div style='font-size:4.8vw; display: flex; justify-content: space-between; flex-direction: row-reverse;'><div>وَإِذَآ</div><div style='flex-grow:0.7'> أُلۡقُواْ مِنۡهَا مَكَانٗا ضَيِّقٗا <a data-content='مقرونة أيديهم إلى أعناقهم بالأغلال' tabindex='0' role='button' class='fake-link tafsir' data-toggle='popover' data-placement='top'>مُّقَرَّنِينَ</a> دَعَوۡاْ هُنَالِكَ </div><div><a data-content='هلاكا فقالوا وَا ثبوراه' tabindex='0' role='button' class='fake-link tafsir' data-toggle='popover' data-placement='top'>ثُبُورٗا</a></div></div><div style='font-size:4.8vw; display: flex; justify-content: space-between; flex-direction: row-reverse;'><div>٣١</div><div style='flex-grow:0.7'> لَّا تَدۡعُواْ ٱلۡيَوۡمَ ثُبُورٗا وَٰحِدٗا وَٱدۡعُواْ ثُبُورٗا كَثِيرٗا </div><div>٤١</div></div><div style='font-size:4.8vw; display: flex; justify-content: space-between; flex-direction: row-reverse;'><div>قُلۡ</div><div style='flex-grow:0.7'> أَذَٰلِكَ خَيۡرٌ أَمۡ جَنَّةُ ٱلۡخُلۡدِ ٱلَّتِي وُعِدَ ٱلۡمُتَّقُونَۚ </div><div>كَانَتۡ</div></div><div style='font-size:4.8vw; display: flex; justify-content: space-between; flex-direction: row-reverse;'><div>لَهُمۡ</div><div style='flex-grow:0.7'> جَزَآءٗ وَمَصِيرٗا ٥١ لَّهُمۡ فِيهَا مَا يَشَآءُونَ </div><div>خَٰلِدِينَۚ</div></div><div style='font-size:4.8vw; display: flex; justify-content: space-between; flex-direction: row-reverse;'><div>كَانَ</div><div style='flex-grow:0.7'> عَلَىٰ رَبِّكَ <a data-content='موعودا حقيقا أن يُسأل ويُطلب' tabindex='0' role='button' class='fake-link tafsir' data-toggle='popover' data-placement='top'>وَعۡدٗا مَّسۡ‍ُٔولٗا</a> ٦١ وَيَوۡمَ يَحۡشُرُهُمۡ </div><div>وَمَا</div></div><div style='font-size:4.8vw; display: flex; justify-content: space-between; flex-direction: row-reverse;'><div>يَعۡبُدُونَ</div><div style='flex-grow:0.7'> مِن دُونِ ٱللَّهِ فَيَقُولُ ءَأَنتُمۡ أَضۡلَلۡتُمۡ </div><div>عِبَادِي</div></div><div style='font-size:4.8vw; display: flex; justify-content: space-between; flex-direction: row-reverse;'><div>هَٰٓؤُلَآءِ</div><div style='flex-grow:0.7'> أَمۡ هُمۡ ضَلُّواْ ٱلسَّبِيلَ ٧١ قَالُواْ سُبۡحَٰنَكَ مَا </div><div>كَانَ</div></div><div style='font-size:4.8vw; display: flex; justify-content: space-between; flex-direction: row-reverse;'><div>يَنۢبَغِي</div><div style='flex-grow:0.7'> لَنَآ أَن نَّتَّخِذَ مِن دُونِكَ مِنۡ أَوۡلِيَآءَ وَلَٰكِن </div><div>مَّتَّعۡتَهُمۡ</div></div><div style='font-size:4.8vw; display: flex; justify-content: space-between; flex-direction: row-reverse;'><div>وَءَابَآءَهُمۡ</div><div style='flex-grow:0.7'> حَتَّىٰ <a data-content='غفلوا عن دلائل الوحدانية' tabindex='0' role='button' class='fake-link tafsir' data-toggle='popover' data-placement='top'>نَسُواْ ٱلذِّكۡرَ</a> وَكَانُواْ <a data-content='هالكين أو فاسدين' tabindex='0' role='button' class='fake-link tafsir' data-toggle='popover' data-placement='top'>قَوۡمَۢا بُورٗا</a> </div><div>٨١</div></div><div style='font-size:4.8vw; display: flex; justify-content: space-between; flex-direction: row-reverse;'><div>فَقَدۡ</div><div style='flex-grow:0.7'> كَذَّبُوكُم بِمَا تَقُولُونَ فَمَا تَسۡتَطِيعُونَ </div><div><a data-content='دفعا للعذاب عن أنفسكم' tabindex='0' role='button' class='fake-link tafsir' data-toggle='popover' data-placement='top'>صَرۡفٗا</a></div></div><div style='font-size:4.8vw; display: flex; justify-content: space-between; flex-direction: row-reverse;'><div>وَلَا</div><div style='flex-grow:0.7'> نَصۡرٗاۚ وَمَن يَظۡلِم مِّنكُمۡ نُذِقۡهُ عَذَابٗا كَبِيرٗا </div><div>٩١</div></div><div style='font-size:4.8vw; display: flex; justify-content: space-between; flex-direction: row-reverse;'><div>وَمَآ</div><div style='flex-grow:0.7'> أَرۡسَلۡنَا قَبۡلَكَ مِنَ ٱلۡمُرۡسَلِينَ إِلَّآ إِنَّهُمۡ </div><div>لَيَأۡكُلُونَ</div></div><div style='font-size:4.8vw; display: flex; justify-content: space-between; flex-direction: row-reverse;'><div>ٱلطَّعَامَ</div><div style='flex-grow:0.7'> وَيَمۡشُونَ فِي ٱلۡأَسۡوَاقِۗ وَجَعَلۡنَا </div><div>بَعۡضَكُمۡ</div></div><div style='font-size:4.8vw; display: flex; justify-content: space-between; flex-direction: row-reverse;'><div>لِبَعۡضٖ</div><div style='flex-grow:0.7'> <a data-content='ابتلاء ومحنة' tabindex='0' role='button' class='fake-link tafsir' data-toggle='popover' data-placement='top'>فِتۡنَةً</a> أَتَصۡبِرُونَۗ وَكَانَ رَبُّكَ بَصِيرٗا </div><div>٠٢</div></div><div style='font-size:4.8vw; display: flex; justify-content: space-between; flex-direction: row-reverse;'></div>",
	"hezb": "ثلاثة أرباع الحزب 36",
	"goze": 18,
	"surahName": "الفُرۡقَانِ"
}