{
	"pageNumber": 528,
	"data": "<div style=\"font-size:4.8vw\">
			<nobr>
				وَأَنَّهُۥ خَلَقَ ٱلزَّوۡجَيۡنِ ٱلذَّكَرَ وَٱلۡأُنثَىٰ ٤٥ مِن نُّطۡفَةٍ إِذَا 
				<a tabindex=\"0\" role=\"button\" class=\"fake-link tafsir\" data-toggle=\"popover\" data-placement=\"top\" data-content=\"تدْفق في الرّحم\">تُمۡنَىٰ
				</a> 
			</nobr>
		</div>
		<div style=\"font-size:4.8vw\">
			<nobr>
				٦٤ وَأَنَّ عَلَيۡهِ 
				<a tabindex=\"0\" role=\"button\" class=\"fake-link tafsir\" data-toggle=\"popover\" data-placement=\"top\" data-content=\"الإحياء بعد الإماتة كما وَعَدَ\">ٱلنَّشۡأَةَ ٱلۡأُخۡرَىٰ
				</a> ٧٤ وَأَنَّهُۥ هُوَ أَغۡنَىٰ 
				<a tabindex=\"0\" role=\"button\" class=\"fake-link tafsir\" data-toggle=\"popover\" data-placement=\"top\" data-content=\"أفقرَ أو أرْضى بما أعْـطَى\">وَأَقۡنَىٰ
				</a> ٨٤ وَأَنَّهُۥ 
			</nobr>
		</div>
		<div style=\"font-size:4.8vw\">
			<nobr>
				هُوَ رَبُّ 
				<a tabindex=\"0\" role=\"button\" class=\"fake-link tafsir\" data-toggle=\"popover\" data-placement=\"top\" data-content=\"كوكبٌ معروف كانوا يعبدونه في الجاهليّة\">ٱلشِّعۡرَىٰ
				</a> ٩٤ وَأَنَّهُۥٓ أَهۡلَكَ 
				<a tabindex=\"0\" role=\"button\" class=\"fake-link tafsir\" data-toggle=\"popover\" data-placement=\"top\" data-content=\"قـَـوْم هودٍ عليه السلام\">عَادًا ٱلۡأُولَىٰ
				</a> ٠٥ 
				<a tabindex=\"0\" role=\"button\" class=\"fake-link tafsir\" data-toggle=\"popover\" data-placement=\"top\" data-content=\"قوم صالح عليه السلام\">وَثَمُودَاْ
				</a> فَمَآ 
			</nobr>
		</div>
		<div style=\"font-size:4.8vw\">
			<nobr>
				أَبۡقَىٰ ١٥ وَقَوۡمَ نُوحٖ مِّن قَبۡلُۖ إِنَّهُمۡ كَانُواْ هُمۡ أَظۡلَمَ وَأَطۡغَىٰ 
			</nobr>
		</div>
		<div style=\"font-size:4.8vw\">
			<nobr>
				٢٥ 
				<a tabindex=\"0\" role=\"button\" class=\"fake-link tafsir\" data-toggle=\"popover\" data-placement=\"top\" data-content=\"قُرى قوم لوطٍ عليه السلام\">وَٱلۡمُؤۡتَفِكَةَ
				</a> 
				<a tabindex=\"0\" role=\"button\" class=\"fake-link tafsir\" data-toggle=\"popover\" data-placement=\"top\" data-content=\"أسْـقـَـطها إلى الأرض بعد رفعها\">أَهۡوَىٰ
				</a> ٣٥ 
				<a tabindex=\"0\" role=\"button\" class=\"fake-link tafsir\" data-toggle=\"popover\" data-placement=\"top\" data-content=\"ألبَسَها وغطّـاها بأنواع من العذاب\">فَغَشَّىٰهَا
				</a> مَا غَشَّىٰ ٤٥ فَبِأَيِّ 
				<a tabindex=\"0\" role=\"button\" class=\"fake-link tafsir\" data-toggle=\"popover\" data-placement=\"top\" data-content=\"نِعَـمِـهِ تعالى ومنها دلائل قدرته\">ءَالَآءِ
				</a> 
			</nobr>
		</div>
		<div style=\"font-size:4.8vw\">
			<nobr>
				رَبِّكَ 
				<a tabindex=\"0\" role=\"button\" class=\"fake-link tafsir\" data-toggle=\"popover\" data-placement=\"top\" data-content=\"تتشكّـك\">تَتَمَارَىٰ
				</a> ٥٥ هَٰذَا نَذِيرٞ مِّنَ 
				<a tabindex=\"0\" role=\"button\" class=\"fake-link tafsir\" data-toggle=\"popover\" data-placement=\"top\" data-content=\"الرّسل أو الأمور المُـخَـوِّفـَـة لهم\">ٱلنُّذُرِ
				</a> ٱلۡأُولَىٰٓ ٦٥ 
				<a tabindex=\"0\" role=\"button\" class=\"fake-link tafsir\" data-toggle=\"popover\" data-placement=\"top\" data-content=\"اقترَبَتْ\">أَزِفَتِ ٱلۡأٓزِفَةُ
				</a> 
			</nobr>
		</div>
		<div style=\"font-size:4.8vw\">
			<nobr>
				٧٥ لَيۡسَ لَهَا مِن دُونِ ٱللَّهِ 
				<a tabindex=\"0\" role=\"button\" class=\"fake-link tafsir\" data-toggle=\"popover\" data-placement=\"top\" data-content=\"نـَفـْـسٌ تكشف أهوالها وشدائدها\">كَاشِفَةٌ
				</a> ٨٥ أَفَمِنۡ هَٰذَا ٱلۡحَدِيثِ 
			</nobr>
		</div>
		<div style=\"font-size:4.8vw\">
			<nobr>
				تَعۡجَبُونَ ٩٥ وَتَضۡحَكُونَ وَلَا تَبۡكُونَ ٠٦ 
				<a tabindex=\"0\" role=\"button\" class=\"fake-link tafsir\" data-toggle=\"popover\" data-placement=\"top\" data-content=\"لاهون غَافـلون\">وَأَنتُمۡ سَٰمِدُونَ
				</a> 
			</nobr>
		</div>
		<div style=\"font-size:4.8vw\" class='no-justify'>
			<nobr>
				١٦ فَٱسۡجُدُواْۤ لِلَّهِۤ وَٱعۡبُدُواْ۩ ٢٦ 
			</nobr>
		</div>
		<div style=\"font-size:4.8vw\" class='no-justify'>
			<nobr>
				سُورَةُ القَمَرِ
			</nobr>
		</div>
		<div style=\"font-size:4.8vw\" class='no-justify'>
			<nobr>
				بِسۡمِ ٱللَّهِ ٱلرَّحۡمَٰنِ ٱلرَّحِيمِ 
			</nobr>
		</div>
		<div style=\"font-size:4.8vw\">
			<nobr>
				ٱقۡتَرَبَتِ ٱلسَّاعَةُ 
				<a tabindex=\"0\" role=\"button\" class=\"fake-link tafsir\" data-toggle=\"popover\" data-placement=\"top\" data-content=\"قدِ انفلق فَـلـْـقـتيْن مُعْجزة له صلى الله عليه وسلم\">وَٱنشَقَّ ٱلۡقَمَرُ
				</a> ١ وَإِن يَرَوۡاْ ءَايَةٗ يُعۡرِضُواْ وَيَقُولُواْ 
			</nobr>
		</div>
		<div style=\"font-size:4.8vw\">
			<nobr>
				
				<a tabindex=\"0\" role=\"button\" class=\"fake-link tafsir\" data-toggle=\"popover\" data-placement=\"top\" data-content=\"دائمٌ أو مُـحْـكمٌ أو ذاهبٌ\">سِحۡرٞ
				</a> مُّسۡتَمِرّٞ ٢ وَكَذَّبُواْ وَٱتَّبَعُوٓاْ أَهۡوَآءَهُمۡۚ وَكُلُّ أَمۡرٖ 
				<a tabindex=\"0\" role=\"button\" class=\"fake-link tafsir\" data-toggle=\"popover\" data-placement=\"top\" data-content=\"مُـنـْــتـهٍ إلى غاية يستقـرّ عليها\">مُّسۡتَقِرّٞ
				</a> ٣ 
			</nobr>
		</div>
		<div style=\"font-size:4.7vw\">
			<nobr>
				وَلَقَدۡ جَآءَهُم مِّنَ ٱلۡأَنۢبَآءِ مَا فِيهِ 
				<a tabindex=\"0\" role=\"button\" class=\"fake-link tafsir\" data-toggle=\"popover\" data-placement=\"top\" data-content=\"ازدجار وانتِهارٌ وردْعٌ عمّا هم فيه من الكفر والضلال\">مُزۡدَجَرٌ
				</a> ٤ حِكۡمَةُۢ بَٰلِغَةٞۖ فَمَا تُغۡنِ 
			</nobr>
		</div>
		<div style=\"font-size:4.8vw\">
			<nobr>
				ٱلنُّذُرُ ٥ فَتَوَلَّ عَنۡهُمۡۘ يَوۡمَ يَدۡعُ ٱلدَّاعِ إِلَىٰ 
				<a tabindex=\"0\" role=\"button\" class=\"fake-link tafsir\" data-toggle=\"popover\" data-placement=\"top\" data-content=\"منكر فظيع (هوْل يوم القيامة)\">شَيۡءٖ نُّكُرٍ
				</a> ٦
			</nobr>
		</div>
		",
	"hezb": "نصف الحزب 53",
	"goze": 27,
	"surahName": "النَّجۡمِ"
}