{
	"pageNumber": 581,
	"data": "<div style='font-size:4.7vw'>
			<nobr>
				أَلَمۡ نَخۡلُقكُّم مِّن 
				<a data-content='مَنِـيّ ضعيف حَقير' tabindex='0' role='button' class='fake-link tafsir' data-toggle='popover' data-placement='top'>
					مَّآءٖ مَّهِينٖ
				</a> 
				٢٠ فَجَعَلۡنَٰهُ فِي 
				<a data-content='مُتمَكّن وهو الرّحِم' tabindex='0' role='button' class='fake-link tafsir' data-toggle='popover' data-placement='top'>
					قَرَارٖ مَّكِينٍ
				</a> 
				٢١ إِلَىٰ قَدَرٖ 
			</nobr>
		</div>
		<div style='font-size:4.8vw'>
			<nobr>
				مَّعۡلُومٖ ٢٢ 
				<a data-content='فـقـَـدّرْنا ذلك تقديرا' tabindex='0' role='button' class='fake-link tafsir' data-toggle='popover' data-placement='top'>
					فَقَدَرۡنَا
				</a> 
				فَنِعۡمَ ٱلۡقَٰدِرُونَ ٢٣ وَيۡلٞ يَوۡمَئِذٖ لِّلۡمُكَذِّبِينَ ٢٤ 
			</nobr>
		</div>
		<div style='font-size:4.8vw'>
			<nobr>
				أَلَمۡ نَجۡعَلِ 
				<a data-content='وعاءًا تضمّ الأحياء على ظهرها' tabindex='0' role='button' class='fake-link tafsir' data-toggle='popover' data-placement='top'>
					ٱلۡأَرۡضَ كِفَاتًا
				</a> 
				٢٥ 
				<a data-content='والأموات في بطنها' tabindex='0' role='button' class='fake-link tafsir' data-toggle='popover' data-placement='top'>
					أَحۡيَآءٗ وَأَمۡوَٰتٗا
				</a> 
				٢٦ وَجَعَلۡنَا فِيهَا رَوَٰسِيَ 
			</nobr>
		</div>
		<div style='font-size:4.8vw'>
			<nobr>
				
				<a data-content='جـِبالا ثوابتَ مُرْتـَفِعات' tabindex='0' role='button' class='fake-link tafsir' data-toggle='popover' data-placement='top'>
					شَٰمِخَٰتٖ
				</a> 
				وَأَسۡقَيۡنَٰكُم 
				<a data-content='حُـلوًا عَذبًـا' tabindex='0' role='button' class='fake-link tafsir' data-toggle='popover' data-placement='top'>
					مَّآءٗ فُرَاتٗا
				</a> 
				٢٧ وَيۡلٞ يَوۡمَئِذٖ لِّلۡمُكَذِّبِينَ ٢٨ 
			</nobr>
		</div>
		<div style='font-size:4.8vw'>
			<nobr>
				ٱنطَلِقُوٓاْ إِلَىٰ مَا كُنتُم بِهِۦ تُكَذِّبُونَ ٢٩ ٱنطَلِقُوٓاْ إِلَىٰ 
				<a data-content='هو دُخان جهنّم' tabindex='0' role='button' class='fake-link tafsir' data-toggle='popover' data-placement='top'>
					ظِلّٖ
				</a> 
				ذِي ثَلَٰثِ 
			</nobr>
		</div>
		<div style='font-size:4.8vw'>
			<nobr>
				
				<a data-content='فِرَقٍ ثلاث كالذوائب' tabindex='0' role='button' class='fake-link tafsir' data-toggle='popover' data-placement='top'>
					شُعَبٖ
				</a> 
				٣٠ 
				<a data-content='لا مظلـّـل من الحرّ' tabindex='0' role='button' class='fake-link tafsir' data-toggle='popover' data-placement='top'>
					لَّا ظَلِيلٖ
				</a> 
				
				<a data-content='لا يَدْفـَعُ شيْئا من حرّه' tabindex='0' role='button' class='fake-link tafsir' data-toggle='popover' data-placement='top'>
					وَلَا يُغۡنِي مِنَ ٱللَّهَبِ
				</a> 
				٣١ إِنَّهَا 
				<a data-content='هو ما تطايَر من النّار مُتفـرّقًـا' tabindex='0' role='button' class='fake-link tafsir' data-toggle='popover' data-placement='top'>
					تَرۡمِي بِشَرَرٖ
				</a> 
				
			</nobr>
		</div>
		<div style='font-size:4.8vw'>
			<nobr>
				
				<a data-content='كلّ شرَرَة كالبناء المُشيّد في العِِظم والإرتفاع' tabindex='0' role='button' class='fake-link tafsir' data-toggle='popover' data-placement='top'>
					كَٱلۡقَصۡرِ
				</a> 
				٣٢ 
				<a data-content='كأنّ الشّرر إبل سودٌ (وتـُسـمّيها العَرَب صفرا) في الكثرة والتـّـتابع وسُرْعة الحركة واللون' tabindex='0' role='button' class='fake-link tafsir' data-toggle='popover' data-placement='top'>
					كَأَنَّهُۥ جِمَٰلَتٞ صُفۡرٞ
				</a> 
				٣٣ وَيۡلٞ يَوۡمَئِذٖ لِّلۡمُكَذِّبِينَ ٣٤ 
			</nobr>
		</div>
		<div style='font-size:4.8vw'>
			<nobr>
				هَٰذَا يَوۡمُ لَا يَنطِقُونَ ٣٥ وَلَا يُؤۡذَنُ لَهُمۡ فَيَعۡتَذِرُونَ ٣٦ وَيۡلٞ يَوۡمَئِذٖ 
			</nobr>
		</div>
		<div style='font-size:4.8vw'>
			<nobr>
				لِّلۡمُكَذِّبِينَ ٣٧ هَٰذَا يَوۡمُ ٱلۡفَصۡلِۖ جَمَعۡنَٰكُمۡ وَٱلۡأَوَّلِينَ ٣٨ فَإِن كَانَ 
			</nobr>
		</div>
		<div style='font-size:4.8vw'>
			<nobr>
				
				<a data-content='حيلة لاتـّـقاء العذاب' tabindex='0' role='button' class='fake-link tafsir' data-toggle='popover' data-placement='top'>
					لَكُمۡ كَيۡدٞ
				</a> 
				فَكِيدُونِ ٣٩ وَيۡلٞ يَوۡمَئِذٖ لِّلۡمُكَذِّبِينَ ٤٠ إِنَّ ٱلۡمُتَّقِينَ 
			</nobr>
		</div>
		<div style='font-size:4.8vw'>
			<nobr>
				فِي ظِلَٰلٖ وَعُيُونٖ ٤١ وَفَوَٰكِهَ مِمَّا يَشۡتَهُونَ ٤٢ كُلُواْ وَٱشۡرَبُواْ هَنِيٓ‍َٔۢا 
			</nobr>
		</div>
		<div style='font-size:4.8vw'>
			<nobr>
				بِمَا كُنتُمۡ تَعۡمَلُونَ ٤٣ إِنَّا كَذَٰلِكَ نَجۡزِي ٱلۡمُحۡسِنِينَ ٤٤ وَيۡلٞ 
			</nobr>
		</div>
		<div style='font-size:4.8vw'>
			<nobr>
				يَوۡمَئِذٖ لِّلۡمُكَذِّبِينَ ٤٥ كُلُواْ وَتَمَتَّعُواْ قَلِيلًا إِنَّكُم مُّجۡرِمُونَ ٤٦ وَيۡلٞ 
			</nobr>
		</div>
		<div style='font-size:4.8vw'>
			<nobr>
				يَوۡمَئِذٖ لِّلۡمُكَذِّبِينَ ٤٧ وَإِذَا قِيلَ لَهُمُ ٱرۡكَعُواْ لَا يَرۡكَعُونَ ٤٨ 
			</nobr>
		</div>
		<div style='font-size:4.8vw'>
			<nobr>
				وَيۡلٞ يَوۡمَئِذٖ لِّلۡمُكَذِّبِينَ ٤٩ فَبِأَيِّ حَدِيثِۢ بَعۡدَهُۥ يُؤۡمِنُونَ ٥٠
			</nobr>
		</div>
		",
	"hezb": "ثلاثة أرباع الحزب 58",
	"goze": 29,
	"surahName": "المُرۡسَلَاتِ"
}