{
	"pageNumber": 153,
	"data": "<div style='font-size:4.8vw; display: flex; justify-content: space-between; flex-direction: row-reverse;'><div>قَالَا</div><div style='flex-grow:0.7'> رَبَّنَا ظَلَمۡنَآ أَنفُسَنَا وَإِن لَّمۡ تَغۡفِرۡ لَنَا وَتَرۡحَمۡنَا </div><div>لَنَكُونَنَّ</div></div><div style='font-size:4.8vw; display: flex; justify-content: space-between; flex-direction: row-reverse;'><div>مِنَ</div><div style='flex-grow:0.7'> ٱلۡخَٰسِرِينَ ٢٣ قَالَ ٱهۡبِطُواْ بَعۡضُكُمۡ لِبَعۡضٍ عَدُوّٞۖ </div><div>وَلَكُمۡ</div></div><div style='font-size:4.8vw; display: flex; justify-content: space-between; flex-direction: row-reverse;'><div>فِي</div><div style='flex-grow:0.7'> ٱلۡأَرۡضِ مُسۡتَقَرّٞ وَمَتَٰعٌ إِلَىٰ حِينٖ ٢٤ قَالَ فِيهَا تَحۡيَوۡنَ </div><div>وَفِيهَا</div></div><div style='font-size:4.8vw; display: flex; justify-content: space-between; flex-direction: row-reverse;'><div>تَمُوتُونَ</div><div style='flex-grow:0.7'> وَمِنۡهَا تُخۡرَجُونَ ٢٥ يَٰبَنِيٓ ءَادَمَ قَدۡ </div><div><a data-content='أعطيناكم ووهبنا لكم' tabindex='0' role='button' class='fake-link tafsir' data-toggle='popover' data-placement='top'>أَنزَلۡنَا عَلَيۡكُمۡ</a></div></div><div style='font-size:4.8vw; display: flex; justify-content: space-between; flex-direction: row-reverse;'><div>لِبَاسٗا</div><div style='flex-grow:0.7'> <a data-content='يستر ويداري عوراتكم' tabindex='0' role='button' class='fake-link tafsir' data-toggle='popover' data-placement='top'>يُوَٰرِي سَوۡءَٰتِكُمۡ</a> <a data-content='لباس زينة أو مالاً' tabindex='0' role='button' class='fake-link tafsir' data-toggle='popover' data-placement='top'>وَرِيشٗاۖ</a> <a data-content='الإيمان وثمراته' tabindex='0' role='button' class='fake-link tafsir' data-toggle='popover' data-placement='top'>وَلِبَاسُ ٱلتَّقۡوَىٰ</a> ذَٰلِكَ </div><div>خَيۡرٞۚ</div></div><div style='font-size:4.8vw; display: flex; justify-content: space-between; flex-direction: row-reverse;'><div>ذَٰلِكَ</div><div style='flex-grow:0.7'> مِنۡ ءَايَٰتِ ٱللَّهِ لَعَلَّهُمۡ يَذَّكَّرُونَ ٢٦ يَٰبَنِيٓ ءَادَمَ </div><div><a data-content='لا يضلنكم ولا يخدعنكم' tabindex='0' role='button' class='fake-link tafsir' data-toggle='popover' data-placement='top'>لَا يَفۡتِنَنَّكُمُ</a></div></div><div style='font-size:4.8vw; display: flex; justify-content: space-between; flex-direction: row-reverse;'><div>ٱلشَّيۡطَٰنُ</div><div style='flex-grow:0.7'> كَمَآ أَخۡرَجَ أَبَوَيۡكُم مِّنَ ٱلۡجَنَّةِ </div><div><a data-content='يزيل عنهما - استلاباً بخداعه' tabindex='0' role='button' class='fake-link tafsir' data-toggle='popover' data-placement='top'>يَنزِعُ عَنۡهُمَا</a></div></div><div style='font-size:4.8vw; display: flex; justify-content: space-between; flex-direction: row-reverse;'><div>لِبَاسَهُمَا</div><div style='flex-grow:0.7'> لِيُرِيَهُمَا سَوۡءَٰتِهِمَآۚ إِنَّهُۥ يَرَىٰكُمۡ هُوَ <a data-content='جنوده أو ذريته' tabindex='0' role='button' class='fake-link tafsir' data-toggle='popover' data-placement='top'>وَقَبِيلُهُۥ</a> </div><div>مِنۡ</div></div><div style='font-size:4.8vw; display: flex; justify-content: space-between; flex-direction: row-reverse;'><div>حَيۡثُ</div><div style='flex-grow:0.7'> لَا تَرَوۡنَهُمۡۗ إِنَّا جَعَلۡنَا ٱلشَّيَٰطِينَ أَوۡلِيَآءَ لِلَّذِينَ لَا </div><div>يُؤۡمِنُونَ</div></div><div style='font-size:4.8vw; display: flex; justify-content: space-between; flex-direction: row-reverse;'><div>٢٧</div><div style='flex-grow:0.7'> وَإِذَا <a data-content='أتوا فعلةً متناهية في القبح' tabindex='0' role='button' class='fake-link tafsir' data-toggle='popover' data-placement='top'>فَعَلُواْ فَٰحِشَةٗ</a> قَالُواْ وَجَدۡنَا عَلَيۡهَآ ءَابَآءَنَا وَٱللَّهُ </div><div>أَمَرَنَا</div></div><div style='font-size:4.8vw; display: flex; justify-content: space-between; flex-direction: row-reverse;'><div>بِهَاۗ</div><div style='flex-grow:0.7'> قُلۡ إِنَّ ٱللَّهَ لَا يَأۡمُرُ بِٱلۡفَحۡشَآءِۖ أَتَقُولُونَ عَلَى ٱللَّهِ مَا لَا </div><div>تَعۡلَمُونَ</div></div><div style='font-size:4.8vw; display: flex; justify-content: space-between; flex-direction: row-reverse;'><div>٢٨</div><div style='flex-grow:0.7'> قُلۡ أَمَرَ رَبِّي <a data-content='بالعدل وهو جميع الطاعات والقُرَب' tabindex='0' role='button' class='fake-link tafsir' data-toggle='popover' data-placement='top'>بِٱلۡقِسۡطِۖ</a> <a data-content='توجهوا إلى عبادته مستقيمين' tabindex='0' role='button' class='fake-link tafsir' data-toggle='popover' data-placement='top'>وَأَقِيمُواْ وُجُوهَكُمۡ</a> </div><div><a data-content='في كل وقت سجود أو مكانه' tabindex='0' role='button' class='fake-link tafsir' data-toggle='popover' data-placement='top'>عِندَ كُلِّ مَسۡجِدٖ</a></div></div><div style='font-size:4.8vw; display: flex; justify-content: space-between; flex-direction: row-reverse;'><div>وَٱدۡعُوهُ</div><div style='flex-grow:0.7'> مُخۡلِصِينَ لَهُ ٱلدِّينَۚ كَمَا بَدَأَكُمۡ تَعُودُونَ </div><div>٢٩</div></div><div style='font-size:4.8vw; display: flex; justify-content: space-between; flex-direction: row-reverse;'><div>فَرِيقًا</div><div style='flex-grow:0.7'> هَدَىٰ وَفَرِيقًا حَقَّ عَلَيۡهِمُ ٱلضَّلَٰلَةُۚ إِنَّهُمُ </div><div>ٱتَّخَذُواْ</div></div><div style='font-size:4.8vw; display: flex; justify-content: space-between; flex-direction: row-reverse;'><div>ٱلشَّيَٰطِينَ</div><div style='flex-grow:0.7'> أَوۡلِيَآءَ مِن دُونِ ٱللَّهِ وَيَحۡسَبُونَ أَنَّهُم مُّهۡتَدُونَ </div><div>٣٠</div></div><div style='font-size:4.8vw; display: flex; justify-content: space-between; flex-direction: row-reverse;'></div>",
	"hezb": "الحزب 16",
	"goze": 8,
	"surahName": "الأَعۡرَافِ"
}