{
	"pageNumber": 153,
	"data": "<div style=\"font-size:4.8vw\"><nobr>قَالَا رَبَّنَا ظَلَمۡنَآ أَنفُسَنَا وَإِن لَّمۡ تَغۡفِرۡ لَنَا وَتَرۡحَمۡنَا لَنَكُونَنَّ </nobr></div>\n<div style=\"font-size:4.8vw\"><nobr>مِنَ ٱلۡخَٰسِرِينَ ٣٢ قَالَ ٱهۡبِطُواْ بَعۡضُكُمۡ لِبَعۡضٍ عَدُوّٞۖ وَلَكُمۡ </nobr></div>\n<div style=\"font-size:4.8vw\"><nobr>فِي ٱلۡأَرۡضِ مُسۡتَقَرّٞ وَمَتَٰعٌ إِلَىٰ حِينٖ ٤٢ قَالَ فِيهَا تَحۡيَوۡنَ وَفِيهَا </nobr></div>\n<div style=\"font-size:4.8vw\"><nobr>تَمُوتُونَ وَمِنۡهَا تُخۡرَجُونَ ٥٢ يَٰبَنِيٓ ءَادَمَ قَدۡ <a tabindex=\"0\" role=\"button\" class=\"fake-link tafsir\" data-toggle=\"popover\" data-placement=\"top\" data-content=\"أعطيناكم ووهبنا لكم\">أَنزَلۡنَا عَلَيۡكُمۡ</a> </nobr></div>\n<div style=\"font-size:4.8vw\"><nobr>لِبَاسٗا <a tabindex=\"0\" role=\"button\" class=\"fake-link tafsir\" data-toggle=\"popover\" data-placement=\"top\" data-content=\"يستر ويداري عوراتكم\">يُوَٰرِي سَوۡءَٰتِكُمۡ</a> <a tabindex=\"0\" role=\"button\" class=\"fake-link tafsir\" data-toggle=\"popover\" data-placement=\"top\" data-content=\"لباس زينة أو مالاً\">وَرِيشٗاۖ</a> <a tabindex=\"0\" role=\"button\" class=\"fake-link tafsir\" data-toggle=\"popover\" data-placement=\"top\" data-content=\"الإيمان وثمراته\">وَلِبَاسُ ٱلتَّقۡوَىٰ</a> ذَٰلِكَ خَيۡرٞۚ </nobr></div>\n<div style=\"font-size:4.8vw\"><nobr>ذَٰلِكَ مِنۡ ءَايَٰتِ ٱللَّهِ لَعَلَّهُمۡ يَذَّكَّرُونَ ٦٢ يَٰبَنِيٓ ءَادَمَ <a tabindex=\"0\" role=\"button\" class=\"fake-link tafsir\" data-toggle=\"popover\" data-placement=\"top\" data-content=\"لا يضلنكم ولا يخدعنكم\">لَا يَفۡتِنَنَّكُمُ</a> </nobr></div>\n<div style=\"font-size:4.8vw\"><nobr>ٱلشَّيۡطَٰنُ كَمَآ أَخۡرَجَ أَبَوَيۡكُم مِّنَ ٱلۡجَنَّةِ <a tabindex=\"0\" role=\"button\" class=\"fake-link tafsir\" data-toggle=\"popover\" data-placement=\"top\" data-content=\"يزيل عنهما - استلاباً بخداعه\">يَنزِعُ عَنۡهُمَا</a> </nobr></div>\n<div style=\"font-size:4.8vw\"><nobr>لِبَاسَهُمَا لِيُرِيَهُمَا سَوۡءَٰتِهِمَآۚ إِنَّهُۥ يَرَىٰكُمۡ هُوَ <a tabindex=\"0\" role=\"button\" class=\"fake-link tafsir\" data-toggle=\"popover\" data-placement=\"top\" data-content=\"جنوده أو ذريته\">وَقَبِيلُهُۥ</a> مِنۡ </nobr></div>\n<div style=\"font-size:4.8vw\"><nobr>حَيۡثُ لَا تَرَوۡنَهُمۡۗ إِنَّا جَعَلۡنَا ٱلشَّيَٰطِينَ أَوۡلِيَآءَ لِلَّذِينَ لَا يُؤۡمِنُونَ </nobr></div>\n<div style=\"font-size:4.8vw\"><nobr>٧٢ وَإِذَا <a tabindex=\"0\" role=\"button\" class=\"fake-link tafsir\" data-toggle=\"popover\" data-placement=\"top\" data-content=\"أتوا فعلةً متناهية في القبح\">فَعَلُواْ فَٰحِشَةٗ</a> قَالُواْ وَجَدۡنَا عَلَيۡهَآ ءَابَآءَنَا وَٱللَّهُ أَمَرَنَا </nobr></div>\n<div style=\"font-size:4.8vw\"><nobr>بِهَاۗ قُلۡ إِنَّ ٱللَّهَ لَا يَأۡمُرُ بِٱلۡفَحۡشَآءِۖ أَتَقُولُونَ عَلَى ٱللَّهِ مَا لَا تَعۡلَمُونَ </nobr></div>\n<div style=\"font-size:4.8vw\"><nobr>٨٢ قُلۡ أَمَرَ رَبِّي <a tabindex=\"0\" role=\"button\" class=\"fake-link tafsir\" data-toggle=\"popover\" data-placement=\"top\" data-content=\"بالعدل وهو جميع الطاعات والقُرَب\">بِٱلۡقِسۡطِۖ</a> <a tabindex=\"0\" role=\"button\" class=\"fake-link tafsir\" data-toggle=\"popover\" data-placement=\"top\" data-content=\"توجهوا إلى عبادته مستقيمين\">وَأَقِيمُواْ وُجُوهَكُمۡ</a> <a tabindex=\"0\" role=\"button\" class=\"fake-link tafsir\" data-toggle=\"popover\" data-placement=\"top\" data-content=\"في كل وقت سجود أو مكانه\">عِندَ كُلِّ مَسۡجِدٖ</a> </nobr></div>\n<div style=\"font-size:4.8vw\"><nobr>وَٱدۡعُوهُ مُخۡلِصِينَ لَهُ ٱلدِّينَۚ كَمَا بَدَأَكُمۡ تَعُودُونَ ٩٢ </nobr></div>\n<div style=\"font-size:4.8vw\"><nobr>فَرِيقًا هَدَىٰ وَفَرِيقًا حَقَّ عَلَيۡهِمُ ٱلضَّلَٰلَةُۚ إِنَّهُمُ ٱتَّخَذُواْ </nobr></div>\n<div style=\"font-size:4.8vw\"><nobr>ٱلشَّيَٰطِينَ أَوۡلِيَآءَ مِن دُونِ ٱللَّهِ وَيَحۡسَبُونَ أَنَّهُم مُّهۡتَدُونَ ٠٣</nobr></div>\n",
	"hezb": "الحزب 16",
	"goze": 8,
	"surahName": "الأَعۡرَافِ"
}