{
	"pageNumber": 231,
	"data": "<div style='font-size:4.8vw; display: flex; justify-content: space-between; flex-direction: row-reverse;'><div>فَلَمَّا</div><div style='flex-grow:0.7'> جَآءَ أَمۡرُنَا جَعَلۡنَا عَٰلِيَهَا سَافِلَهَا وَأَمۡطَرۡنَا </div><div>عَلَيۡهَا</div></div><div style='font-size:4.8vw; display: flex; justify-content: space-between; flex-direction: row-reverse;'><div>حِجَارَةٗ</div><div style='flex-grow:0.7'> مِّن <a data-content='طين طُبخ بالنّار كالفخّار' tabindex='0' role='button' class='fake-link tafsir' data-toggle='popover' data-placement='top'>سِجِّيلٖ</a> <a data-content='متتابع أو مجموع معدّ للعذاب' tabindex='0' role='button' class='fake-link tafsir' data-toggle='popover' data-placement='top'>مَّنضُودٖ</a> ٢٨ <a data-content='معلمة العذاب' tabindex='0' role='button' class='fake-link tafsir' data-toggle='popover' data-placement='top'>مُّسَوَّمَةً</a> عِندَ </div><div>رَبِّكَۖ</div></div><div style='font-size:4.8vw; display: flex; justify-content: space-between; flex-direction: row-reverse;'><div>وَمَا</div><div style='flex-grow:0.7'> هِيَ مِنَ ٱلظَّٰلِمِينَ بِبَعِيدٖ ٣٨ ۞وَإِلَىٰ مَدۡيَنَ </div><div>أَخَاهُمۡ</div></div><div style='font-size:4.8vw; display: flex; justify-content: space-between; flex-direction: row-reverse;'><div>شُعَيۡبٗاۚ</div><div style='flex-grow:0.7'> قَالَ يَٰقَوۡمِ ٱعۡبُدُواْ ٱللَّهَ مَا لَكُم مِّنۡ إِلَٰهٍ </div><div>غَيۡرُهُۥۖ</div></div><div style='font-size:4.8vw; display: flex; justify-content: space-between; flex-direction: row-reverse;'><div>وَلَا</div><div style='flex-grow:0.7'> تَنقُصُواْ ٱلۡمِكۡيَالَ وَٱلۡمِيزَانَۖ إِنِّيٓ </div><div><a data-content='بسعة تُغنيكم عن التطفيف' tabindex='0' role='button' class='fake-link tafsir' data-toggle='popover' data-placement='top'>أَرَىٰكُم بِخَيۡرٖ</a></div></div><div style='font-size:4.8vw; display: flex; justify-content: space-between; flex-direction: row-reverse;'><div>وَإِنِّيٓ</div><div style='flex-grow:0.7'> أَخَافُ عَلَيۡكُمۡ عَذَابَ <a data-content='مُهلك' tabindex='0' role='button' class='fake-link tafsir' data-toggle='popover' data-placement='top'>يَوۡمٖ مُّحِيطٖ</a> ٤٨ </div><div>وَيَٰقَوۡمِ</div></div><div style='font-size:4.8vw; display: flex; justify-content: space-between; flex-direction: row-reverse;'><div>أَوۡفُواْ</div><div style='flex-grow:0.7'> ٱلۡمِكۡيَالَ وَٱلۡمِيزَانَ <a data-content='بالعدل بلا زيادة ولا نُقصان' tabindex='0' role='button' class='fake-link tafsir' data-toggle='popover' data-placement='top'>بِٱلۡقِسۡطِۖ</a> <a data-content='لا تنقصوا' tabindex='0' role='button' class='fake-link tafsir' data-toggle='popover' data-placement='top'>وَلَا تَبۡخَسُواْ</a> </div><div>ٱلنَّاسَ</div></div><div style='font-size:4.8vw; display: flex; justify-content: space-between; flex-direction: row-reverse;'><div>أَشۡيَآءَهُمۡ</div><div style='flex-grow:0.7'> <a data-content='لا تُفسدوا أشدّ الإفساد' tabindex='0' role='button' class='fake-link tafsir' data-toggle='popover' data-placement='top'>وَلَا تَعۡثَوۡاْ</a> فِي ٱلۡأَرۡضِ مُفۡسِدِينَ ٥٨ </div><div><a data-content='ما أبقاه لكم من الحلال' tabindex='0' role='button' class='fake-link tafsir' data-toggle='popover' data-placement='top'>بَقِيَّتُ</a></div></div><div style='font-size:4.8vw; display: flex; justify-content: space-between; flex-direction: row-reverse;'><div>ٱللَّهِ</div><div style='flex-grow:0.7'> خَيۡرٞ لَّكُمۡ إِن كُنتُم مُّؤۡمِنِينَۚ وَمَآ أَنَا۠ </div><div>عَلَيۡكُم</div></div><div style='font-size:4.8vw; display: flex; justify-content: space-between; flex-direction: row-reverse;'><div><a data-content='برقيب فأجازيكم بأعمالكم' tabindex='0' role='button' class='fake-link tafsir' data-toggle='popover' data-placement='top'>بِحَفِيظٖ</a> ٦٨ قَالُواْ يَٰشُعَيۡبُ أَصَلَوٰتُكَ تَأۡمُرُكَ أَن نَّتۡرُكَ</div><div style='flex-grow:0.7'></div><div>نَّتۡرُكَ</div></div><div style='font-size:4.8vw; display: flex; justify-content: space-between; flex-direction: row-reverse;'><div>مَا</div><div style='flex-grow:0.7'> يَعۡبُدُ ءَابَآؤُنَآ أَوۡ أَن نَّفۡعَلَ فِيٓ أَمۡوَٰلِنَا مَا نَشَٰٓؤُاْۖ </div><div>إِنَّكَ</div></div><div style='font-size:4.8vw; display: flex; justify-content: space-between; flex-direction: row-reverse;'><div>لَأَنتَ</div><div style='flex-grow:0.7'> ٱلۡحَلِيمُ ٱلرَّشِيدُ ٧٨ قَالَ يَٰقَوۡمِ <a data-content='أخبروني' tabindex='0' role='button' class='fake-link tafsir' data-toggle='popover' data-placement='top'>أَرَءَيۡتُمۡ</a> إِن </div><div>كُنتُ</div></div><div style='font-size:4.8vw; display: flex; justify-content: space-between; flex-direction: row-reverse;'><div>عَلَىٰ</div><div style='flex-grow:0.7'> <a data-content='هداية وبصيرة' tabindex='0' role='button' class='fake-link tafsir' data-toggle='popover' data-placement='top'>بَيِّنَةٖ</a> مِّن رَّبِّي وَرَزَقَنِي مِنۡهُ رِزۡقًا حَسَنٗاۚ وَمَآ أُرِيدُ </div><div>أَنۡ</div></div><div style='font-size:4.8vw; display: flex; justify-content: space-between; flex-direction: row-reverse;'><div>أُخَالِفَكُمۡ</div><div style='flex-grow:0.7'> إِلَىٰ مَآ أَنۡهَىٰكُمۡ عَنۡهُۚ إِنۡ أُرِيدُ إِلَّا </div><div>ٱلۡإِصۡلَٰحَ</div></div><div style='font-size:4.8vw; display: flex; justify-content: space-between; flex-direction: row-reverse;'><div>مَا</div><div style='flex-grow:0.7'> ٱسۡتَطَعۡتُۚ وَمَا تَوۡفِيقِيٓ إِلَّا بِٱللَّهِۚ عَلَيۡهِ تَوَكَّلۡتُ وَإِلَيۡهِ أُنِيبُ </div><div>٨٨</div></div><div style='font-size:4.8vw; display: flex; justify-content: space-between; flex-direction: row-reverse;'></div>",
	"hezb": "الحزب 24",
	"goze": 12,
	"surahName": "هُودٍ"
}